Workbook

Sheet Dynamic Dashboard
A1: DYNAMIC CORE MENTORS DASHBOARD
A2: Auto-Updates When Source Data Changes | VSM | PSP | TPI
A3: Last Updated: | B3: =TODAY() -> 45945
A5: 📊 CORE MENTORS DATA (AUTO-UPDATING)
A7: Mentor Type | B7: Prompt Count | C7: Response Count | D7: Coverage % | E7: Status
A8: PSP | B8: =COUNTA('PSP Mentor Prompts'!B:B)-1 -> 44 | C8: =COUNTA('PSP Mentor Prompts'!C:C)-1 -> 44 | D8: =IF(B8=0,0,C8/B8*100) -> 100 | E8: =IF(D8>=90,"Excellent",IF(D8>=70,"Good",IF(D8>=50,"Fair","Needs Attention"))) -> Excellent
A9: VSM | B9: =COUNTA('VSM Mentor Prompts'!B:B)-1 -> 31 | C9: =COUNTA('VSM Mentor Prompts'!C:C)-1 -> 31 | D9: =IF(B9=0,0,C9/B9*100) -> 100 | E9: =IF(D9>=90,"Excellent",IF(D9>=70,"Good",IF(D9>=50,"Fair","Needs Attention"))) -> Excellent
A10: TPI | B10: =COUNTA('TPI Mentor Prompts'!B:B)-1 -> 21 | C10: =COUNTA('TPI Mentor Prompts'!C:C)-1 -> 21 | D10: =IF(B10=0,0,C10/B10*100) -> 100 | E10: =IF(D10>=90,"Excellent",IF(D10>=70,"Good",IF(D10>=50,"Fair","Needs Attention"))) -> Excellent
A11: TOTAL | B11: =SUM(B8:B10) -> 96 | C11: =SUM(C8:C10) -> 96 | D11: =IF(B11=0,0,C11/B11*100) -> 100 | E11: Combined
A14: Mentor | B14: Percentage
A15: PSP | B15: =IF(B11=0,0,B8/B11*100) -> 45.833333
A16: 📋 LIVE METRICS SUMMARY
A17: TPI | B17: =IF(B11=0,0,B10/B11*100) -> 21.875
A18: Total Core Mentors: | B18: 3
A19: Total Prompts: | B19: =B11 -> 96
A20: Total Responses: | B20: =C11 -> 96
A21: Overall Coverage: | B21: =D11 -> 100
A22: Average per Mentor: | B22: =B11/3 -> 32
A23: Top Performer: | B23: =INDEX(A8:A10,MATCH(MAX(B8:B10),B8:B10,0)) -> PSP
A35: 💡 HOW IT WORKS:
A36: ✅ This dashboard updates AUTOMATICALLY when you change data in mentor sheets
A37: ✅ Add/remove prompts in PSP/VSM/TPI sheets - dashboard reflects changes instantly
A38: ✅ Charts and metrics recalculate automatically - no Python script needed
A39: ✅ Coverage percentages update as you add responses
A40: ✅ Top performer automatically changes based on current data

Sheet Charts Dashboard
A1: CORE MENTORS ANALYTICS DASHBOARD
A2: VSM | PSP | TPI Mentors Only | Generated: 2025-09-02 12:14:39
A4: 📊 SECTION 1: CORE MENTORS OVERVIEW
A6: Mentor Type | B6: Prompt Count | C6: Percentage
A7: PSP | B7: 44 | C7: 45.8%
A8: VSM | B8: 31 | C8: 32.3%
A9: TPI | B9: 21 | C9: 21.9%
A10: TOTAL | B10: 96 | C10: 100.0%
A29: 📈 SECTION 2: RESPONSE COVERAGE - CORE MENTORS
A31: Mentor Type | B31: Total Prompts | C31: Responses | D31: Coverage % | E31: Status
A32: PSP | B32: 44 | C32: 44 | D32: 100.0% | E32: Excellent
A33: VSM | B33: 31 | C33: 31 | D33: 100.0% | E33: Excellent
A34: TPI | B34: 21 | C34: 21 | D34: 100.0% | E34: Excellent
A54: 🎯 SECTION 3: PERFORMANCE COMPARISON - CORE MENTORS
A56: Mentor Type | B56: Prompts | C56: Coverage % | D56: Performance Score | E56: Rank
A57: PSP | B57: 44 | C57: 100.0% | D57: 100.0 | E57: 🥇 1
A58: VSM | B58: 31 | C58: 100.0% | D58: 82.3 | E58: 🥈 2
A59: TPI | B59: 21 | C59: 100.0% | D59: 68.6 | E59: 🥉 3
A79: 📋 CORE MENTORS EXECUTIVE SUMMARY
A81: Core Mentors Analyzed: | B81: PSP, VSM, TPI
A82: Total Prompts (Core): | B82: 96
A83: Average per Mentor: | B83: 32.0
A84: Average Coverage: | B84: 100.0%
A85: Top Performer: | B85: PSP (44 prompts)
A86: Analysis Date: | B86: 2025-09-02 12:14
A87: Data Quality: | B87: High - Core mentors only
A88: Filtered Out: | B88: New_Prompts, G&I (inactive)

Sheet PSP Mentor Prompts
A1: SL | B1: Prompts | C1: Response | D1: Sources | E1: Status | F1: Tester Remarks | G1: Developer Remarks | H1: Date
A2: 1 | B2: Upload my PSR and critique it | C2: To effectively critique your Problem Solving Report (PSR), we need to consider several key aspects based on the Fortive Business System (FBS) and the Problem Solving Process (PSP). Here’s a structured approach to evaluating your PSR: ### Key Components of a Problem Solving Report (PSR) 1. **Clarity of Problem Statement**: - Ensure that the problem statement is clearly defined. It should articulate the gap between the current state and the desired state. For example, if the issue is related to production downtime, specify the current downtime percentage and the target percentage. 2. **Artifacts and Insights**: - The PSR should include various artifacts that capture insights and learnings from the DIVE process. This could include data analysis, brainstorming results, and any relevant metrics. For instance, if you conducted a root cause analysis, summarize the findings and how they inform your next steps. 3. **Actions Taken**: - Document the actions that have been implemented to address the problem. This should include both immediate actions and long-term strategies. For example, if a quality defect was identified, detail the corrective actions taken and any preventive measures planned. 4. **Progress Tracking**: - Include metrics that track progress towards resolving the problem. This could be in the form of KPIs (Key Performance Indicators) relevant to your issue. For example, if you are addressing customer churn, include metrics like retention rates before and after implementing changes. 5. **Next Steps and Follow-Up**: - Clearly outline the next steps in the problem-solving process. This should include who is responsible for each action and the timeline for completion. For instance, if further analysis is needed, specify who will conduct it and by when. ### Example Critique Framework - **Problem Statement**: Is it specific and measurable? Does it clearly define the gap? - **Data and Artifacts**: Are the insights well-documented? Do they support the problem statement? - **Actions**: Are the actions taken logical and relevant? Are they documented with timelines? - **Metrics**: Are the metrics used to track progress appropriate and clearly presented? - **Next Steps**: Are the next steps actionable and assigned to specific team members? ### Conclusion By ensuring that your PSR addresses these components, you can enhance its effectiveness as a communication tool within the PSP framework. This will not only help in closing the gap between the current and desired states but also facilitate better collaboration and understanding among team members. If you would like to share specific sections of your PSR for a more detailed critique, please upload it, and I can provide targeted feedback based on the criteria outlined above. Would you like to proceed with that? | D2: https://fortive.sharepoint.com/:p:/r/sites/FTV-TheFort/_layouts/15/Doc.aspx?sourcedoc=%7B78185926-2BBA-4280-8D70-52802D36723D%7D&file=PSP%20tied%20to%20elearning.pptx&action=edit&mobileredirect=true | E2: Bad | F2: P.Lee: This is a prompt and the quality of the answer is dependent on the PSR loaded and if it is answering it correctly to actutally critique it. The prompt and the answer does not align. The prompt seems to ask to upload and reads the PSR. This should be the last one we test because this is dependent on the different scenarios and different version of PSR that gets upload be critiqued. I dont know how well the AI does it's critiquing ability yet.
A3: 2 | B3: Generate 7 ways to come up with a Pareto | C3: Creating a Pareto Chart is an effective way to visualize and prioritize problems based on the 80/20 rule, which helps teams focus on the most significant issues impacting their processes. Here are seven ways to develop a Pareto Chart, incorporating the principles from the Fortive Business System (FBS): ### 1. **Identify the Problem Area** - **Action**: Begin by clearly defining the problem you want to analyze. This could be related to quality defects, customer complaints, or production delays. - **Example**: If you are experiencing high customer churn, specify that as your problem area. ### 2. **Collect Data** - **Action**: Gather relevant data that reflects the frequency or impact of the issues within the defined problem area. This data can come from various sources such as customer feedback, production logs, or quality reports. - **Example**: For customer churn, collect data on the reasons customers cite for leaving, such as service issues, pricing, or product quality. ### 3. **Categorize the Data** - **Action**: Organize the collected data into categories that represent the different types of issues or causes. This helps in identifying patterns. - **Example**: Categorize reasons for churn into groups like "Service Quality," "Pricing," "Product Features," etc. ### 4. **Count the Frequency of Each Category** - **Action**: Tally the occurrences of each category to determine which issues are most prevalent. This step is crucial for creating the visual representation of the Pareto Chart. - **Example**: If "Service Quality" accounts for 50 complaints, "Pricing" for 30, and "Product Features" for 20, these counts will form the basis of your chart. ### 5. **Calculate Cumulative Percentages** - **Action**: Calculate the cumulative percentage of each category to visualize the impact of each issue relative to the total. This helps in identifying the most significant contributors. - **Example**: If the total number of complaints is 100, "Service Quality" would represent 50%, "Pricing" 30%, and "Product Features" 20%. The cumulative percentages would help illustrate how these categories contribute to the overall problem. ### 6. **Create the Pareto Chart** - **Action**: Using the frequency and cumulative percentage data, create the Pareto Chart. The left axis typically represents the frequency of issues, while the right axis represents the cumulative percentage. - **Example**: Plot the categories on the x-axis and their corresponding frequencies on the y-axis, adding a line graph for cumulative percentages. ### 7. **Analyze and Prioritize Actions** - **Action**: Review the completed Pareto Chart to identify the "vital few" issues that contribute to the majority of the problems. Focus your problem-solving efforts on these areas for maximum impact. - **Example**: If "Service Quality" is identified as the most significant issue, prioritize actions to improve service processes, training, or customer support. ### Conclusion By following these steps, you can effectively create a Pareto Chart that highlights the most critical issues within your problem area. This visual tool not only aids in understanding where to focus efforts but also aligns with the FBS principles of delivering extraordinary results and closing the gap between current and desired states. If you need further assistance in creating a specific Pareto Chart or analyzing your data, feel free to ask! Would you like to explore any of these steps in more detail? | D3: https://fortive.sharepoint.com/:p:/r/sites/FTV-TheFort/_layouts/15/Doc.aspx?sourcedoc=%7B78185926-2BBA-4280-8D70-52802D36723D%7D&file=PSP%20tied%20to%20elearning.pptx&action=edit&mobileredirect=true | E3: Bad | F3: P.Lee: The prompt and and answer is not related. The prompt assumption is I am uploading a dataset to go with it. Then the ask is to generate different ways to slice the data. The answer is more of an answer on different steps to consider when trying to create a Pareto.
A4: 3 | B4: Please generate 20 questions that I should ask that will help me dig deeper and gain insights on my problem | C4: To effectively dig deeper into a problem and gain valuable insights, it's essential to ask targeted questions that align with the Problem Solving Process (PSP) as outlined in the Fortive Business System (FBS). Here are 20 questions categorized into different areas that can help you explore the problem comprehensively: ### Understanding the Problem 1. **What is the specific problem we are facing?** - Clarifies the issue at hand. 2. **What are the symptoms of this problem?** - Helps identify observable effects. 3. **What is the gap between the current state (Actual) and the desired state (Standard)?** - Establishes a clear understanding of the discrepancy. 4. **When did this problem first occur?** - Provides context and timeline for the issue. 5. **How frequently does this problem occur?** - Assesses the severity and impact of the problem. ### Analyzing Causes 6. **What are the potential root causes of this problem?** - Encourages exploration of underlying issues. 7. **Who is affected by this problem, and how?** - Identifies stakeholders and their experiences. 8. **What data do we have that supports our understanding of this problem?** - Prompts review of existing evidence. 9. **Are there any patterns or trends associated with this problem?** - Looks for recurring themes or correlations. 10. **What assumptions are we making about this problem?** - Challenges preconceived notions that may hinder analysis. ### Exploring Solutions 11. **What solutions have we tried in the past, and what were the outcomes?** - Evaluates previous efforts and their effectiveness. 12. **What resources do we have available to address this problem?** - Assesses capabilities and constraints. 13. **What would success look like if we resolved this problem?** - Defines clear objectives for resolution. 14. **Who needs to be involved in the problem-solving process?** - Identifies key team members and stakeholders. 15. **What are the potential risks associated with different solutions?** - Considers the implications of various approaches. ### Implementing and Sustaining Solutions 16. **How will we measure the success of our solution?** - Establishes metrics for evaluation. 17. **What is the timeline for implementing potential solutions?** - Sets expectations for progress. 18. **How will we communicate our findings and solutions to the team?** - Ensures transparency and collaboration. 19. **What steps will we take to sustain improvements once implemented?** - Focuses on long-term success and prevention of recurrence. 20. **How will we gather feedback after implementing the solution?** - Plans for ongoing assessment and adjustment. ### Conclusion These questions are designed to guide you through a thorough exploration of your problem, aligning with the PSP framework to ensure that you identify the root causes and develop effective solutions. By systematically addressing these areas, you can close the gap between your current state and desired outcomes, ultimately delivering extraordinary results. If you would like to discuss any specific questions further or need assistance in applying these questions to your situation, feel free to ask! Would you like to explore any particular area in more detail? | D4: https://fortive.sharepoint.com/:p:/r/sites/FTV-TheFort/_layouts/15/Doc.aspx?sourcedoc=%7B2679DEA0-53E4-46A4-80CC-69F4534B9231%7D&file=fortive-problem-solving-process-%20tied%20to%20elearning.pptx&action=edit&mobileredirect=true | E4: Neutral | F4: P.Lee: The prompt is asking questions about how to generate more insights on the problem statement. The insights provided on the "Understanding the Problem" + "possibly the causes" are OK but the comments after that does not relate to the question. Solutions and sustainment of them is not what the prompt is asking for. the question is on the D in the DIVE and we are giving answers about "I&V" section. REsponses like : I can provide you with general guidelines and questions to consider, See below .... then ask if they can share the problem statement we can create a more specific set of questions to consider.
A5: 4 | B5: Can you create a level 1 and level 2 pareto? | C5: Creating Level 1 and Level 2 Pareto Charts is an effective way to analyze problems and identify their root causes using the 80/20 rule, as established by Vilfredo Pareto. Below is a structured approach to developing both types of Pareto Charts, incorporating the principles from the Fortive Business System (FBS). ### Level 1 Pareto Chart **Purpose**: The Level 1 Pareto Chart helps identify where the problems are occurring by categorizing and quantifying the frequency of issues. #### Steps to Create a Level 1 Pareto Chart: 1. **Identify the Problem Area**: - Define the specific problem you want to analyze. For example, if you are experiencing quality defects in a manufacturing process, specify that as your focus. 2. **Collect Data**: - Gather data on the frequency of different types of defects or issues. This could come from quality control reports, customer complaints, or production logs. - **Example Data**: - Defect Type A: 50 occurrences - Defect Type B: 30 occurrences - Defect Type C: 20 occurrences - Defect Type D: 10 occurrences 3. **Categorize the Data**: - Organize the data into categories based on the types of defects or issues identified. 4. **Create the Chart**: - Plot the categories on the x-axis and the frequency of occurrences on the y-axis. Use bars to represent the frequency of each defect type. - Add a cumulative percentage line to show the cumulative impact of the issues. 5. **Analyze the Chart**: - Identify the "vital few" issues that contribute to the majority of the problems. For instance, if Defect Type A accounts for 50% of the total defects, it should be prioritized for resolution. ### Level 2 Pareto Chart **Purpose**: The Level 2 Pareto Chart focuses on understanding why the problems are occurring by analyzing the root causes. #### Steps to Create a Level 2 Pareto Chart: 1. **Build on Level 1 Findings**: - Use the insights gained from the Level 1 Pareto Chart to identify potential root causes for the most significant issues. 2. **Identify the "WHY"**: - Each team member should brainstorm and identify at least five different potential causes for the top issues identified in the Level 1 chart. - **Example Causes for Defect Type A**: - Lack of training for operators - Inadequate maintenance of equipment - Poor quality of raw materials - Inefficient production processes - Lack of quality checks 3. **Create an Affinity Diagram**: - Organize the identified causes into an affinity diagram to group similar ideas and identify patterns. 4. **Select Top Causes**: - As a team, select the top two most insightful causes based on the affinity diagram. These will be the focus for further analysis. 5. **Collect Data for Selected Causes**: - Gather data to support the analysis of these root causes. This could include training records, maintenance logs, or supplier quality reports. 6. **Create the Level 2 Pareto Chart**: - Plot the selected root causes on the x-axis and their frequency or impact on the y-axis. This chart will help visualize which root causes are most significant. 7. **Analyze and Plan Actions**: - Use the Level 2 Pareto Chart to prioritize actions that address the root causes. For example, if "Lack of training for operators" is identified as a major cause, develop a training program to mitigate this issue. ### Conclusion By following these steps, you can effectively create both Level 1 and Level 2 Pareto Charts that will help you understand where problems are occurring and why they are happening. This structured approach aligns with the Problem Solving Process (PSP) and supports continuous improvement efforts within the Fortive Business System. If you need further assistance in applying these steps to a specific problem or creating the charts, feel free to ask! Would you like to explore any particular aspect in more detail? | D5: https://fortive.sharepoint.com/:p:/r/sites/FTV-TheFort/_layouts/15/Doc.aspx?sourcedoc=%7B78185926-2BBA-4280-8D70-52802D36723D%7D&file=PSP%20tied%20to%20elearning.pptx&action=edit&mobileredirect=true | E5: Neutral | F5: P.LEE: The prompt is can you create a L1 & L2 Pareto. Answer should be "YES" and but they need to load the excel data so KATA mentor can do it. Prompt wasn’t asking what a L1 and L2 is or what the steps are to create one. Should ask if they would like to know if they want to know the difference between the 2 or the steps to create one.
A6: 5 | B6: What gemba evidence do I need to support the 5 why I just created? | C6: To effectively support the "5 Whys" analysis with Gemba evidence, it’s essential to gather data and observations that directly relate to the identified root causes of the problem. Gemba, which means "the real place" in Japanese, emphasizes going to the location where the work is done to observe processes and gather firsthand information. Here’s how to approach collecting Gemba evidence to support your analysis: ### 1. **Observation of Processes** - **Action**: Spend time observing the specific processes related to the problem. Look for inefficiencies, bottlenecks, or deviations from standard operating procedures. - **Example**: If the issue is related to production delays, observe the production line to identify where delays occur and what factors contribute to them (e.g., equipment malfunctions, operator errors). ### 2. **Engagement with Employees** - **Action**: Talk to employees who are directly involved in the processes. Their insights can provide valuable context and highlight issues that may not be immediately visible. - **Example**: Ask operators about their experiences with the equipment or processes. They may reveal that a specific machine frequently breaks down or that they lack the necessary training to perform their tasks efficiently. ### 3. **Review of Performance Metrics** - **Action**: Collect and analyze relevant performance metrics that can provide quantitative evidence of the problem. - **Example**: Look at key performance indicators (KPIs) such as cycle times, defect rates, or downtime statistics. If you find that defect rates have increased, this data can support your analysis of why quality issues are occurring. ### 4. **Documentation of Standard Procedures** - **Action**: Compare current practices with documented standard operating procedures (SOPs) to identify discrepancies. - **Example**: If the SOP states that a particular quality check should be performed at a specific stage, but it is not being done, this evidence can help explain why defects are occurring. ### 5. **Analysis of Historical Data** - **Action**: Review historical data related to the problem to identify trends or recurring issues. - **Example**: If you notice that a particular defect type has been increasing over time, this historical evidence can support your findings in the "5 Whys" analysis. ### 6. **Visual Evidence** - **Action**: Take photographs or videos of the processes, equipment, or areas where problems are occurring. Visual evidence can be compelling in illustrating issues. - **Example**: If there are safety hazards or cluttered workspaces contributing to inefficiencies, visual documentation can highlight these problems effectively. ### 7. **Feedback from Customers** - **Action**: Gather feedback from customers regarding their experiences with the product or service. This can provide insights into external perceptions of the problem. - **Example**: If customers report issues with product quality, this feedback can support your analysis of why quality checks may be failing. ### Conclusion By collecting this Gemba evidence, you will be able to substantiate the findings from your "5 Whys" analysis with concrete data and observations. This approach aligns with the Problem Solving Process (PSP) and helps ensure that your solutions are grounded in reality, ultimately leading to more effective problem resolution. If you need further assistance in gathering specific types of Gemba evidence or applying these concepts to your situation, feel free to ask! Would you like to explore any particular aspect in more detail? | D6: https://fortive.sharepoint.com/:p:/r/sites/FTV-TheFort/_layouts/15/Doc.aspx?sourcedoc=%7B2679DEA0-53E4-46A4-80CC-69F4534B9231%7D&file=fortive-problem-solving-process-%20tied%20to%20elearning.pptx&action=edit&mobileredirect=true | E6: Good | F6: P.Lee: It is providing different ways or examples on obtaining Gemba evidence.
A7: 6 | B7: Does my logic of my 5 whys makes sense to get to my root cause? Please analyze and provide feedback | C7: To analyze the logic of your "5 Whys" and provide feedback on whether it effectively leads to the root cause, we can follow a structured approach based on the principles of the Problem Solving Process (PSP) within the Fortive Business System (FBS). Here’s how to evaluate your analysis: ### 1. **Clarity of the Problem Statement** - **Assessment**: Ensure that your initial problem statement is clear and specific. It should define the gap between the current state (Actual) and the desired state (Standard). - **Example**: If your problem statement is "Production delays are occurring," clarify what the expected production rate is versus the actual rate. ### 2. **Logical Flow of the 5 Whys** - **Assessment**: Each "Why" should logically lead to the next question, progressively digging deeper into the causes of the problem. - **Example**: - **Why are we experiencing production delays?** (e.g., Equipment breakdown) - **Why is the equipment breaking down?** (e.g., Lack of maintenance) - **Why is there a lack of maintenance?** (e.g., Insufficient training for maintenance staff) - **Why is there insufficient training?** (e.g., No training program in place) - **Why is there no training program?** (e.g., Budget constraints) ### 3. **Validation of Causes** - **Assessment**: Each identified cause should be validated with evidence, ideally through Gemba observations or data analysis. This ensures that the identified causes are not assumptions but are based on real observations. - **Example**: If you state that "lack of maintenance" is a cause, provide evidence from maintenance logs or interviews with maintenance staff that supports this claim. ### 4. **Limiting to Actual Causes** - **Assessment**: The final causes identified should be limited to no more than three actual causes, as recommended in the FBS methodology. This helps focus efforts on the most impactful areas. - **Example**: If your final causes are "lack of training" and "budget constraints," ensure these are the most significant contributors to the problem. ### 5. **Alignment with PSP Framework** - **Assessment**: Ensure that your "5 Whys" analysis aligns with the overall PSP framework, which emphasizes understanding the problem, identifying root causes, and planning actions to close the gap. - **Example**: After identifying the root causes, outline specific actions that can be taken to address them, such as developing a training program or reallocating budget resources. ### Conclusion and Feedback If your "5 Whys" follow a logical progression, are supported by evidence, and lead to a limited number of actual causes, then your analysis is sound and effectively identifies the root cause. If any of these elements are lacking, consider revisiting those areas to strengthen your analysis. If you would like to share your specific "5 Whys" for a more detailed review or need assistance in refining your logic, feel free to provide that information! Would you like to explore any particular aspect further? | D7: https://fortive.sharepoint.com/:p:/r/sites/FTV-TheFort/_layouts/15/Doc.aspx?sourcedoc=%7B2679DEA0-53E4-46A4-80CC-69F4534B9231%7D&file=fortive-problem-solving-process-%20tied%20to%20elearning.pptx&action=edit&mobileredirect=true | E7: Bad | F7: P.LEE this is not a generic prompt that can be answered with a standard answser, the 5 why's is dependendent on the PSR loaded. Not a good prompt to use. Unless the prompt is changed to "What are charateristics of a good 5 why" might be closer to the answer on column C
A8: 7 | B8: how should I look at things differently if it is a Caused vs. a Created problem? | C8: Understanding the distinction between "Caused" and "Created" problems is crucial in the Problem Solving Process (PSP) within the Fortive Business System (FBS). This differentiation influences how you approach problem analysis and resolution. Here’s how to look at these two types of problems differently: ### 1. **Definition of Terms** - **Caused Problems**: These are issues that arise from external factors or events outside of the system or process. They are typically beyond the control of the organization and can include things like supply chain disruptions, regulatory changes, or natural disasters. - **Created Problems**: These are internal issues that stem from the organization’s own processes, systems, or decisions. They often result from inefficiencies, poor practices, or lack of adherence to standards. ### 2. **Approach to Problem Analysis** - **For Caused Problems**: - **Focus on External Factors**: Investigate the external circumstances that led to the problem. This may involve analyzing market conditions, supplier performance, or environmental factors. - **Example**: If a production line is halted due to a supplier failing to deliver materials on time, the problem is caused by the supplier's actions, not by internal processes. - **Action**: Develop contingency plans or alternative sourcing strategies to mitigate the impact of external disruptions. - **For Created Problems**: - **Focus on Internal Processes**: Analyze the internal systems and practices that contributed to the problem. This may involve reviewing workflows, employee training, or adherence to standard operating procedures. - **Example**: If a quality defect occurs due to improper training of staff on equipment usage, the problem is created by the organization’s training processes. - **Action**: Implement process improvements, such as enhanced training programs or revised standard operating procedures, to prevent recurrence. ### 3. **Root Cause Analysis** - **For Caused Problems**: - **Use External Data**: Gather data from external sources to understand the context of the problem. This could include market analysis reports, supplier performance metrics, or industry benchmarks. - **Example**: Analyzing market trends that led to increased demand for a product can help understand why a supplier was unable to meet delivery timelines. - **For Created Problems**: - **Conduct Internal Assessments**: Utilize tools like the "5 Whys" or Pareto analysis to identify root causes within the organization. Engage with employees at the Gemba to gather insights on process inefficiencies. - **Example**: If a defect is traced back to a lack of quality checks, the root cause analysis should focus on the quality control processes in place. ### 4. **Solution Development** - **For Caused Problems**: - **Develop Adaptive Strategies**: Solutions may involve adapting to external changes, such as finding new suppliers or adjusting production schedules based on market conditions. - **Example**: If a natural disaster affects supply chains, consider diversifying suppliers or increasing inventory levels to buffer against future disruptions. - **For Created Problems**: - **Implement Process Improvements**: Solutions should focus on improving internal processes, enhancing training, or refining workflows to eliminate the root causes. - **Example**: If employee errors are leading to defects, a solution could involve implementing a more robust training program and regular performance reviews. ### Conclusion By recognizing whether a problem is caused by external factors or created by internal processes, you can tailor your analysis and solutions accordingly. This distinction is vital for effective problem-solving and aligns with the PSP framework, enabling you to close the gap between the current state and desired outcomes. If you have specific examples of problems you are facing, feel free to share them for more tailored guidance! Would you like to explore any particular aspect further? | D8: https://fortive.sharepoint.com/:p:/r/sites/FTV-TheFort/_layouts/15/Doc.aspx?sourcedoc=%7B2679DEA0-53E4-46A4-80CC-69F4534B9231%7D&file=fortive-problem-solving-process-%20tied%20to%20elearning.pptx&action=edit&mobileredirect=true | E8: Bad | F8: P.Lee: This is a main question, and the answer is saying caused problems are all caused by issues beyond our control. And created is focusing on internal processes which is wrong. Should review where we are getting the info and if we need to correct it somewhere if it is indicating that. The new PSP deck has it all spelled out too why it is called Caused vs. Created and with distinct definitions https://fortive.sharepoint.com/sites/FBS/SiteAssets/SitePages/PSP/PSP-Facilitator-Deck-2025--Final.pptx?web=1
A9: 8 | B9: Create a Run chart that graphically helps show case the timing of of the problem | C9: Creating a Run Chart is an effective way to visualize the timing of a problem, helping to identify trends, patterns, and anomalies over time. Below is a structured approach to creating a Run Chart, incorporating the principles from the Fortive Business System (FBS). ### Steps to Create a Run Chart 1. **Define the Problem Statement Using TAGS** - **TAGS Framework**: Ensure you have a clear problem statement that includes: - **Target**: The desired outcome or standard. - **Actual**: The current performance or measurement. - **Gap**: The difference between the target and actual performance. - **Scope**: The context or boundaries of the problem. - **Example**: If the problem is related to production delays, your TAGS might look like this: - **Target**: 95% on-time delivery - **Actual**: 85% on-time delivery - **Gap**: 10% - **Scope**: Production line A over the last quarter. 2. **Collect Data** - Gather data points that reflect the performance over time. This data should be collected in the same units as used in your TAGS statement. - **Example Data**: Collect weekly on-time delivery percentages for the last 12 weeks: - Week 1: 90% - Week 2: 85% - Week 3: 80% - Week 4: 88% - Week 5: 82% - Week 6: 75% - Week 7: 87% - Week 8: 80% - Week 9: 78% - Week 10: 85% - Week 11: 83% - Week 12: 90% 3. **Set Up the Run Chart** - **X-Axis**: Represent time (e.g., weeks). - **Y-Axis**: Represent the performance metric (e.g., on-time delivery percentage). - **Plot the Data**: Mark each data point on the chart according to the week and the corresponding on-time delivery percentage. 4. **Add Reference Lines** - **Target Line**: Draw a horizontal line at the target percentage (e.g., 95%). - **Average Line**: Optionally, calculate and draw a line representing the average performance over the period. - **Example**: If the average on-time delivery over the 12 weeks is 82%, draw a horizontal line at 82%. 5. **Analyze the Chart** - Look for trends, spikes, or drops in performance. Identify any patterns that correlate with specific events or changes in the process. - **Example Analysis**: If you notice a significant drop in on-time delivery in Week 6, investigate what occurred during that week (e.g., equipment failure, staffing issues). ### Example of a Run Chart Here’s a simplified representation of how your Run Chart might look: ``` On-Time Delivery Percentage 100% | 95% |------------------- Target Line -------- 90% | * * * 85% | * * * * 80% | * * * * 75% | * * * * 70% |___________________________________________ Week 1 Week 2 Week 3 Week 4 Week 5 Week 6 Week 7 Week 8 Week 9 Week 10 Week 11 Week 12 ``` ### Conclusion By following these steps, you can create a Run Chart that visually represents the timing of the problem and helps identify trends and potential causes. This aligns with the PSP framework, allowing you to analyze the gap between your actual performance and desired outcomes effectively. If you need further assistance in creating the chart or analyzing specific data points, feel free to ask! Would you like to explore any particular aspect further? | D9: https://fortive.sharepoint.com/:p:/r/sites/FTV-TheFort/_layouts/15/Doc.aspx?sourcedoc=%7B2679DEA0-53E4-46A4-80CC-69F4534B9231%7D&file=fortive-problem-solving-process-%20tied%20to%20elearning.pptx&action=edit&mobileredirect=true | E9: Bad | F9: P.Lee This is not a good prompt without any data uploaded, in order to test this, the same data file should be loaded to compare if it is still providing you with the consistent answer. Asking it the way it is not helpful to see if it is working, all you can validate is it is responding. better prompt question might be "what are the steps in creating a run chart?" , "how do I create a run chart?" , or "what should I be looking out for when I create a run chart?" Questions that will provide consistent answers not situational TAGS: TREND, ACTUAL, GAP, STANDARD - Not Target, Actual, Gap. Scope
A10: 9 | B10: what is a glide path and how do I create an action plan that can support the timing? | C10: A **glide path** is a strategic plan that outlines the steps and timeline necessary to achieve a specific goal or improvement target. It provides a clear trajectory for progress, ensuring that actions are aligned with desired outcomes and that stakeholders understand the timing and expectations involved. In the context of the Fortive Business System (FBS) and the Problem Solving Process (PSP), creating an effective action plan that supports the glide path is essential for successful implementation. ### Steps to Create an Action Plan that Supports the Glide Path 1. **Define the Improvement Priority** - **Action**: Clearly identify the specific process or area that needs improvement. This should be based on data analysis, such as findings from a Kaizen event or a run chart. - **Example**: If the goal is to reduce production downtime, specify that as your improvement priority. 2. **Set Clear Objectives** - **Action**: Establish measurable objectives that align with the glide path. These should be specific, measurable, achievable, relevant, and time-bound (SMART). - **Example**: Reduce production downtime by 20% within the next quarter. 3. **Identify Key Actions** - **Action**: List the specific actions required to achieve the objectives. Each action should contribute directly to closing the gap between the current state and the desired state. - **Example**: - Conduct a root cause analysis of downtime incidents. - Implement a preventive maintenance schedule. - Train staff on equipment operation and maintenance. 4. **Assign Responsibilities** - **Action**: Designate an action plan owner for each task. This ensures accountability and clarity regarding who is responsible for each action. - **Example**: Assign the maintenance manager to oversee the implementation of the preventive maintenance schedule. 5. **Establish a Timeline** - **Action**: Create a timeline for each action, indicating when it should start and when it should be completed. This timeline should align with the glide path, ensuring that all actions are scheduled to support the overall goal. - **Example**: - Root cause analysis: Start in Week 1, complete by Week 2. - Preventive maintenance schedule: Develop by Week 3, implement by Week 4. - Staff training: Schedule for Week 5. 6. **Monitor Progress** - **Action**: Set up regular check-ins to monitor progress against the glide path. This allows for adjustments to be made if necessary and ensures that the team stays on track. - **Example**: Weekly meetings to review progress on action items and discuss any challenges. 7. **Document and Communicate** - **Action**: Document the action plan in a clear format, including all the elements above. Share this document with all stakeholders to ensure transparency and alignment. - **Example**: Use a table format to outline the action plan, including columns for the improvement priority, action items, responsible parties, timelines, and comments. ### Example Action Plan Table | Improvement Priority | Action Item | Action Plan Owner | Timing | Comments/Specific Time | |------------------------------|------------------------------------------|-------------------|-----------------------|---------------------------------| | Reduce Production Downtime | Conduct root cause analysis | Maintenance Manager| Week 1 - Week 2 | Analyze downtime incidents | | | Implement preventive maintenance schedule | Maintenance Manager| Week 3 - Week 4 | Schedule maintenance tasks | | | Train staff on equipment operation | Training Coordinator| Week 5 | Develop training materials | ### Conclusion By following these steps, you can create a comprehensive action plan that supports the glide path for your improvement initiative. This structured approach ensures that all actions are aligned with the desired outcomes and that progress is monitored effectively, ultimately leading to successful implementation of improvements within the Fortive Business System. If you need further assistance in developing specific elements of your action plan or have questions about the glide path concept, feel free to ask! Would you like to explore any particular aspect further? | D10: https://fortive.sharepoint.com/:p:/r/sites/FTV-TheFort/_layouts/15/Doc.aspx?sourcedoc=%7B2679DEA0-53E4-46A4-80CC-69F4534B9231%7D&file=fortive-problem-solving-process-%20tied%20to%20elearning.pptx&action=edit&mobileredirect=true | E10: Neutral | F10: P.Lee: Is there a reference somewhere in the PSP training deck on SMART objectives? A picture of a glide path would be very helpful here. The action plan answers are good and I do like the timeline creation part. A key piece of info that should point out and usually used during the DEFINE state and the VERIFY stages of the DIVE process. During the DEFINE Stage, the glide path shows where we will end up after a certime time frame if we continue at the current course. During the VERIFY stage, after we identify the CM to the root causes, it visually shows of the CM identified is sufficient to eliminate the gap at the timeframe needed. If not, then additional CM might be needed.
A11: 10 | B11: on the DEFINE stage, what are the key things that I need to be on a look out for? | C11: In the DEFINE stage of the Problem Solving Process (PSP) within the Fortive Business System (FBS), it is crucial to establish a clear understanding of the problem at hand. This stage sets the foundation for effective problem resolution and involves several key elements that you should be on the lookout for: ### 1. **Clear Problem Statement** - **Action**: Formulate a concise and specific problem statement that captures the essence of the issue. This statement should articulate the gap between the current state (Actual) and the desired state (Standard). - **Example**: Instead of saying "Production is slow," a clearer problem statement would be "Production line A is operating at 70% efficiency, while the target efficiency is 90%, resulting in a 20% gap." ### 2. **Understanding the Scope** - **Action**: Define the boundaries of the problem. Identify what is in-scope and out-of-scope for the analysis to ensure that the focus remains on relevant factors. - **Example**: If the problem involves production delays, clarify whether you are focusing on a specific product line, shift, or time period. ### 3. **Data Collection** - **Action**: Gather relevant data that supports your understanding of the problem. This may include historical performance data, customer feedback, or operational metrics. - **Example**: Collect data on production rates, downtime incidents, and quality defects over the past few months to identify trends and patterns. ### 4. **Stakeholder Involvement** - **Action**: Engage with key stakeholders who are affected by or have insights into the problem. Their perspectives can provide valuable context and help validate the problem statement. - **Example**: Conduct interviews or surveys with operators, supervisors, and quality control personnel to gather insights on the challenges they face. ### 5. **Identifying the Impact** - **Action**: Assess the impact of the problem on the organization. This includes understanding how the problem affects productivity, quality, customer satisfaction, and overall business objectives. - **Example**: Determine how the 20% efficiency gap translates into lost revenue or increased costs, which can help prioritize the urgency of addressing the problem. ### 6. **Use of TAGS Framework** - **Action**: Utilize the TAGS framework (Target, Actual, Gap, Scope) to structure your problem definition. This framework helps ensure that all critical aspects of the problem are considered. - **Example**: - **Target**: 90% efficiency - **Actual**: 70% efficiency - **Gap**: 20% - **Scope**: Production line A for the last quarter. ### 7. **Run Chart Preparation** - **Action**: Prepare to create a run chart that visually represents the data over time. This chart will help illustrate trends and fluctuations related to the problem. - **Example**: Set up a run chart with time on the x-axis and production efficiency on the y-axis to visualize how performance has changed over the past months. ### Conclusion By focusing on these key elements during the DEFINE stage, you can establish a solid foundation for your problem-solving efforts. This clarity will guide subsequent stages of the PSP, ensuring that the team is aligned and equipped to address the identified issues effectively. If you have specific aspects of the DEFINE stage you would like to explore further or need assistance with a particular problem, feel free to ask! Would you like to dive deeper into any of these areas? | D11: https://fortive.sharepoint.com/:p:/r/sites/FTV-TheFort/_layouts/15/Doc.aspx?sourcedoc=%7B2679DEA0-53E4-46A4-80CC-69F4534B9231%7D&file=fortive-problem-solving-process-%20tied%20to%20elearning.pptx&action=edit&mobileredirect=true | E11: Neutral | F11: P.Lee all right answers, I think what is missing is the topic of RATIONALE and TEAM selection. It identifies the steps needed to create the TAGS, problem statement is good but the process in creating that should also be taken into consideration as this is a team sport and ensuring this is a problem worth solving.
A12: 11 | B12: on the INVESTIGATE stage, what are the key things that I need to be on a look out for? | C12: In the INVESTIGATE stage of the Problem Solving Process (PSP) within the Fortive Business System (FBS), the focus is on thoroughly analyzing the problem to identify its root causes. This stage is critical for ensuring that the solutions developed later are based on a comprehensive understanding of the issue. Here are the key elements to look out for during the INVESTIGATE stage: ### 1. **Data Collection** - **Action**: Gather relevant quantitative and qualitative data that pertains to the problem. This data should help illustrate the extent of the issue and provide insights into potential causes. - **Example**: If the problem is related to increased defect rates in production, collect data on defect types, frequencies, and any relevant operational metrics over a defined period. ### 2. **Observation at the Gemba** - **Action**: Go to the actual location where the problem occurs (Gemba) to observe processes firsthand. This allows you to see the problem in context and gather insights that may not be evident from data alone. - **Example**: Observe the production line during different shifts to identify patterns in defects or inefficiencies, and engage with operators to understand their experiences. ### 3. **Engagement with Stakeholders** - **Action**: Involve key stakeholders, including employees, supervisors, and customers, to gather diverse perspectives on the problem. Their insights can provide valuable context and help validate findings. - **Example**: Conduct interviews or focus groups with team members to discuss their observations and experiences related to the problem. ### 4. **Identifying Patterns and Trends** - **Action**: Analyze the collected data for patterns or trends that may indicate underlying issues. Look for correlations between different data points that could help identify root causes. - **Example**: If you notice that defect rates spike during specific shifts or after certain maintenance activities, this could indicate a need for further investigation into those areas. ### 5. **Utilizing Problem-Solving Tools** - **Action**: Employ various problem-solving tools and methodologies, such as the "5 Whys," Fishbone Diagram (Ishikawa), or Pareto Analysis, to systematically analyze the problem and identify root causes. - **Example**: Use a Fishbone Diagram to categorize potential causes of defects into categories such as People, Processes, Equipment, and Materials. ### 6. **Validation of Findings** - **Action**: Validate the identified causes with evidence. Ensure that the conclusions drawn from the investigation are supported by data and observations. - **Example**: If a lack of training is identified as a root cause, review training records and gather feedback from employees about their training experiences. ### 7. **Documentation of Insights** - **Action**: Document all findings, insights, and data collected during the investigation. This documentation will be crucial for the next stages of the PSP and for communicating findings to stakeholders. - **Example**: Create a report summarizing the investigation process, data analysis, and identified root causes, which can be shared with the team and leadership. ### Conclusion By focusing on these key elements during the INVESTIGATE stage, you can ensure a comprehensive understanding of the problem and its root causes. This thorough analysis will set the stage for effective problem resolution and align with the overall goals of the Fortive Business System. If you have specific aspects of the INVESTIGATE stage you would like to explore further or need assistance with a particular problem, feel free to ask! Would you like to dive deeper into any of these areas? | D12: https://fortive.sharepoint.com/:p:/r/sites/FTV-TheFort/_layouts/15/Doc.aspx?sourcedoc=%7B2679DEA0-53E4-46A4-80CC-69F4534B9231%7D&file=fortive-problem-solving-process-%20tied%20to%20elearning.pptx&action=edit&mobileredirect=true | E12: Neutral | F12: P.Lee: All correct answers but incomplete. During investigate the main step here is working on the Paretos and that should be a main topic, it is embedded in the **Utilizing Problem solving tools** Missing topics like 1)L1 Pareto in relation to Pareto 2 (a subset and there is linkage. 2) the cummulative %, what is acceptable?, 3the Pareto units of measure should be the same units as the GAP. 4) 5 whys logic making sense going forward and backward asking "BECAUSE" and "AS A RESULT/ THEREFORE"
A13: 12 | B13: On the VERIFY stage, what are the key things that I need to be on a look out for? | C13: In the VERIFY stage of the Problem Solving Process (PSP) within the Fortive Business System (FBS), the focus is on confirming that the implemented solutions effectively address the identified problems and that the desired outcomes are being achieved. This stage is critical for ensuring that the actions taken have led to meaningful improvements. Here are the key elements to look out for during the VERIFY stage: ### 1. **Establish Clear Metrics for Success** - **Action**: Define specific metrics that will be used to evaluate the effectiveness of the implemented solutions. These metrics should align with the objectives set during the DEFINE stage. - **Example**: If the goal was to reduce production downtime, metrics could include on-time delivery rates, production efficiency percentages, and the frequency of downtime incidents. ### 2. **Collect Data Post-Implementation** - **Action**: Gather data after the solutions have been implemented to assess their impact. This data should be compared against the baseline data collected prior to the implementation. - **Example**: If you implemented a new maintenance schedule, collect data on equipment downtime and production rates over a defined period after the changes were made. ### 3. **Analyze Results Against Targets** - **Action**: Analyze the collected data to determine whether the results meet the established targets. Look for trends and patterns that indicate whether the solutions are effective. - **Example**: If the target was to achieve a 20% reduction in downtime, calculate the actual reduction and assess whether it meets the target. ### 4. **Engage Stakeholders for Feedback** - **Action**: Involve key stakeholders, including team members and supervisors, to gather qualitative feedback on the changes. Their insights can provide context to the data and highlight any unforeseen issues. - **Example**: Conduct surveys or hold meetings to discuss how the changes have affected daily operations and whether any new challenges have arisen. ### 5. **Identify Any Unintended Consequences** - **Action**: Look for any unintended consequences that may have resulted from the implemented solutions. These could be negative impacts that were not anticipated during the planning phase. - **Example**: If a new process was introduced to speed up production, check if it has led to an increase in defects or employee dissatisfaction. ### 6. **Document Findings and Adjustments** - **Action**: Document all findings from the verification process, including successes, challenges, and any adjustments that need to be made. This documentation will be valuable for future problem-solving efforts. - **Example**: Create a report summarizing the results of the verification process, including data analysis, stakeholder feedback, and any necessary changes to the implemented solutions. ### 7. **Plan for Continuous Improvement** - **Action**: Use the insights gained during the VERIFY stage to inform future improvement initiatives. Continuous improvement is a core principle of the FBS, and lessons learned should be applied to ongoing processes. - **Example**: If certain aspects of the solution were effective while others were not, consider refining the approach and planning additional kaizen events to address remaining issues. ### Conclusion By focusing on these key elements during the VERIFY stage, you can ensure that the solutions implemented are effective and that the desired outcomes are being achieved. This thorough verification process aligns with the overall goals of the Fortive Business System and supports continuous improvement efforts. If you have specific aspects of the VERIFY stage you would like to explore further or need assistance with a particular problem, feel free to ask! Would you like to dive deeper into any of these areas? | D13: https://fortive.sharepoint.com/:p:/r/sites/FTV-TheFort/_layouts/15/Doc.aspx?sourcedoc=%7B2679DEA0-53E4-46A4-80CC-69F4534B9231%7D&file=fortive-problem-solving-process-%20tied%20to%20elearning.pptx&action=edit&mobileredirect=true | E13: Neutral | F13: P.Lee All correct and good answers but is missing a few key items. VERIFY stage,1) we need to ensure the CM identified is improving the GAP 2) ensure that we have enough CM to 3) ensure that there is Temporary and Permanent CM. 4) Target dates are not all at the end of the year, and there is sense of urgency to improve things. 5) CM will delivery results at the expected timeline by using the GLIDEPATH to visually see when will mitigate the gap.
A14: 13 | B14: on the ENSURE sustainment stage, what are the key things that I need to look out for? | C14: In the ENSURE sustainment stage of the Problem Solving Process (PSP) within the Fortive Business System (FBS), the focus is on maintaining the improvements achieved through previous stages and ensuring that the solutions implemented continue to deliver the desired results over time. This stage is critical for embedding changes into the organizational culture and preventing regression to old habits. Here are the key elements to look out for during the ENSURE sustainment stage: ### 1. **Standardization of Processes** - **Action**: Develop and document standard operating procedures (SOPs) that reflect the new processes and improvements. This ensures that everyone follows the same methods and practices. - **Example**: If a new maintenance schedule was implemented to reduce equipment downtime, create an SOP that outlines the maintenance tasks, frequency, and responsible personnel. ### 2. **Training and Development** - **Action**: Provide ongoing training for employees to ensure they are familiar with the new processes and understand their roles in sustaining improvements. - **Example**: Conduct training sessions for staff on the updated procedures and any new tools or technologies introduced during the improvement process. ### 3. **Monitoring and Measurement** - **Action**: Establish metrics and key performance indicators (KPIs) to continuously monitor the effectiveness of the implemented solutions. Regularly review these metrics to identify any deviations from expected performance. - **Example**: If the goal was to maintain a 20% reduction in downtime, track downtime metrics weekly and compare them against the target to ensure compliance. ### 4. **Feedback Mechanisms** - **Action**: Create channels for employees to provide feedback on the new processes. This can help identify issues early and allow for adjustments to be made as needed. - **Example**: Implement regular check-in meetings or anonymous surveys to gather input from team members about the effectiveness of the changes and any challenges they face. ### 5. **Leadership Engagement** - **Action**: Ensure that leadership remains engaged and supportive of the changes. Their commitment is crucial for fostering a culture of continuous improvement. - **Example**: Leaders should regularly communicate the importance of the changes and recognize team members who contribute to sustaining improvements. ### 6. **Continuous Improvement Culture** - **Action**: Foster a culture of continuous improvement where employees are encouraged to identify further opportunities for enhancement. This mindset helps sustain improvements and drives ongoing success. - **Example**: Encourage teams to hold regular kaizen events to explore new areas for improvement and to celebrate successes achieved through the changes. ### 7. **Regular Reviews and Audits** - **Action**: Schedule periodic reviews and audits of the processes to ensure compliance with the new standards and to assess the effectiveness of the improvements. - **Example**: Conduct quarterly audits to evaluate adherence to the new maintenance schedule and to identify any areas that may need additional support or adjustment. ### Conclusion By focusing on these key elements during the ENSURE sustainment stage, you can effectively maintain the improvements achieved through the PSP. This structured approach aligns with the overall goals of the Fortive Business System, ensuring that the organization continues to deliver extraordinary results and closes the gap between current performance and desired outcomes. If you have specific aspects of the ENSURE sustainment stage you would like to explore further or need assistance with a particular problem, feel free to ask! Would you like to dive deeper into any of these areas? | E14: Neutral | F14: P.Lee Good decent answers, but lacking a few key things. 1) no mention og how the sustaintmaint is going to happen. What is the review cadence of the progress and most important how are they incorporating Daily Management process into the ENSURE SUSTAINMENT step of PSP.
A15: 14 | B15: Provide me with a blank PSR form | C15: A Problem Solving Report (PSR) is an essential communication tool within the Fortive Business System (FBS) that captures the current understanding and actions being taken to address a problem. Below is a blank template for a PSR that you can use to document your problem-solving efforts. This template includes key sections that should be filled out to ensure comprehensive reporting. ### Blank Problem Solving Report (PSR) Template --- **Problem Solving Report (PSR)** **Date:** _______________________ **Team Members:** _______________________________________________________ **Problem Statement:** - **Target:** ___________________________________________________________ - **Actual:** ___________________________________________________________ - **Gap:** _____________________________________________________________ - **Scope:** ___________________________________________________________ --- **1. Problem Description** - Briefly describe the problem and its impact on the organization. - ______________________________________________________________________ - ______________________________________________________________________ **2. Data Collection** - Summarize the data collected to understand the problem. - ______________________________________________________________________ - ______________________________________________________________________ **3. Root Cause Analysis** - List the identified root causes using tools such as the "5 Whys" or Fishbone Diagram. - ______________________________________________________________________ - ______________________________________________________________________ **4. Action Plan** - Outline the actions to be taken to address the root causes. - **Action Item:** ______________________________________________________ - **Owner:** ___________________________________________________________ - **Due Date:** ________________________________________________________ - **Status:** ___________________________________________________________ --- **5. Monitoring and Measurement** - Describe how the effectiveness of the actions will be measured. - ______________________________________________________________________ - ______________________________________________________________________ **6. Follow-Up Actions** - List any follow-up actions required to ensure sustainment of improvements. - ______________________________________________________________________ - ______________________________________________________________________ **7. Additional Notes** - Include any other relevant information or insights. - ______________________________________________________________________ - ______________________________________________________________________ --- ### Example of a Completed PSR Section **Problem Statement:** - **Target:** 95% on-time delivery - **Actual:** 85% on-time delivery - **Gap:** 10% - **Scope:** Production line A for Q1 2023 **1. Problem Description** - The production line A has been consistently missing on-time delivery targets, impacting customer satisfaction and revenue. **2. Data Collection** - Collected data on delivery rates over the past three months, identifying a trend of increasing delays. **3. Root Cause Analysis** - Identified root causes include equipment breakdowns, insufficient staffing, and lack of training. **4. Action Plan** - **Action Item:** Implement a preventive maintenance schedule - **Owner:** Maintenance Manager - **Due Date:** March 15, 2023 - **Status:** In Progress --- ### Conclusion This blank PSR template can be customized to fit the specific needs of your problem-solving efforts. By documenting your findings and actions in a structured manner, you can enhance communication and ensure that all team members are aligned in addressing the problem effectively. If you need further assistance in filling out the PSR or have specific questions about any section, feel free to ask! Would you like to explore any particular aspect further? | E15: Bad | F15: P.Lee This is not what the prompt is asking for. It is asking for a blank PSR form. The answer should be a link to the FBS Templates. It should not be recreating it by typing something up.
A16: 15 | B16: What is the difference and the relationship of a Level 1 to a Level 2 pareto? | C16: The distinction between Level 1 and Level 2 Pareto Charts is essential for effectively analyzing problems and understanding their root causes within the Problem Solving Process (PSP) of the Fortive Business System (FBS). Here’s a comprehensive overview of the differences and the relationship between the two types of Pareto Charts: ### Level 1 Pareto Chart (Where) - **Purpose**: The Level 1 Pareto Chart focuses on identifying **where** the problems are occurring. It visually represents the frequency or impact of various issues, allowing teams to prioritize which problems to address first. - **Data Representation**: This chart typically displays categories of problems or issues on the x-axis and their corresponding frequencies or impacts on the y-axis. It often includes a cumulative percentage line to show the overall impact of the identified issues. - **Example**: If a company is experiencing revenue misses, a Level 1 Pareto Chart might show the revenue shortfall by region: - Southeast Region: $180K (72%) - West Region: $50K (20%) - East Region: $20K (8%) - **Insight**: This chart helps teams quickly identify which regions are contributing most significantly to the revenue miss, guiding them to focus their efforts on the Southeast Region first. ### Level 2 Pareto Chart (Why) - **Purpose**: The Level 2 Pareto Chart delves deeper into the **why** behind the problems identified in the Level 1 chart. It analyzes the root causes of the issues, providing insights into the factors contributing to the problems. - **Data Representation**: This chart categorizes the reasons for the problems identified in the Level 1 chart. It may show the frequency of different root causes or contributing factors, again with a cumulative percentage line. - **Example**: Continuing with the revenue miss example, a Level 2 Pareto Chart might analyze the reasons for the revenue shortfall: - Sales Coverage: $140K (56%) - Campaign Effectiveness: $30K (12%) - Auto Verticals: $10K (4%) - **Insight**: This chart helps teams understand that inadequate sales coverage is the primary reason for the revenue miss, prompting them to investigate and address this specific issue. ### Relationship Between Level 1 and Level 2 Pareto Charts - **Sequential Analysis**: The Level 1 Pareto Chart serves as the starting point for analysis, identifying where the problems are. Once the significant issues are identified, the Level 2 Pareto Chart is used to explore the underlying causes of those issues. - **Complementary Insights**: Together, these charts provide a comprehensive view of the problem. The Level 1 chart highlights the most pressing issues, while the Level 2 chart reveals the root causes that need to be addressed to resolve those issues effectively. - **Guiding Problem-Solving Efforts**: By using both charts, teams can prioritize their problem-solving efforts. They can first tackle the most significant issues identified in the Level 1 chart and then focus on the root causes revealed in the Level 2 chart. ### Conclusion In summary, the Level 1 Pareto Chart identifies **where** problems are occurring, while the Level 2 Pareto Chart investigates **why** those problems are happening. Together, they form a powerful analytical tool that guides teams through the Problem Solving Process, enabling them to deliver extraordinary results and close the gap between current performance and desired outcomes. If you have further questions or need assistance with creating these charts, feel free to ask! Would you like to explore any specific examples or applications of these concepts? | E16: Good | F16: P.Lee Answer is correct.
A17: 16 | B17: How is the Level 2 pareto related to the 5 whys? | C17: The Level 2 Pareto Chart and the "5 Whys" technique are both essential tools in the Problem Solving Process (PSP) within the Fortive Business System (FBS). They serve complementary purposes in identifying and analyzing the root causes of problems. Here’s a detailed explanation of how they are related: ### Level 2 Pareto Chart - **Purpose**: The Level 2 Pareto Chart focuses on identifying **why** problems are occurring. It categorizes the root causes of issues identified in the Level 1 Pareto Chart, which highlights **where** the problems are happening. - **Data Representation**: This chart displays the frequency or impact of various root causes, allowing teams to prioritize which causes to address first based on their significance. - **Example**: If a Level 1 Pareto Chart shows that production delays are primarily occurring in the Southeast Region, the Level 2 Pareto Chart might analyze the reasons for these delays, such as: - Equipment failure: 60% - Staffing shortages: 25% - Process inefficiencies: 15% ### The 5 Whys Technique - **Purpose**: The "5 Whys" is a root cause analysis tool used to explore the underlying causes of a problem by repeatedly asking "why" until the fundamental cause is identified. This technique helps drill down into the specifics of why an issue is occurring. - **Process**: Starting with a problem statement, you ask "why" the problem exists, and for each answer, you continue to ask "why" until you reach the root cause. - **Example**: If the problem is identified as "equipment failure," the 5 Whys might look like this: 1. **Why** did the equipment fail? → Because it was not maintained properly. 2. **Why** was it not maintained properly? → Because the maintenance schedule was not followed. 3. **Why** was the maintenance schedule not followed? → Because staff were not trained on the importance of maintenance. 4. **Why** were staff not trained? → Because there was no training program in place. 5. **Why** was there no training program? → Because of budget constraints. ### Relationship Between Level 2 Pareto and 5 Whys 1. **Complementary Analysis**: - The Level 2 Pareto Chart provides a visual representation of the most significant root causes identified from the Level 1 chart. It helps prioritize which causes to investigate further using the 5 Whys technique. - For example, if the Level 2 Pareto Chart indicates that "equipment failure" is a major contributor to production delays, the team can then apply the 5 Whys to explore this specific cause in detail. 2. **Focused Investigation**: - By using the Level 2 Pareto Chart to identify the most impactful root causes, teams can focus their 5 Whys analysis on those areas that will yield the greatest benefit in terms of problem resolution. - This targeted approach ensures that resources are used efficiently and that the most critical issues are addressed first. 3. **Validation of Findings**: - The insights gained from the 5 Whys can validate or refine the findings from the Level 2 Pareto Chart. If the 5 Whys analysis reveals additional underlying causes not initially identified, these can be incorporated into the problem-solving efforts. - For instance, if the 5 Whys uncover that a lack of training is a root cause, this information can be added to the Level 2 analysis, prompting further action. ### Conclusion In summary, the Level 2 Pareto Chart and the 5 Whys technique are interconnected tools that enhance the problem-solving process. The Level 2 Pareto Chart identifies and prioritizes root causes, while the 5 Whys technique provides a structured approach to deeply analyze those causes. Together, they enable teams to effectively address problems and implement sustainable solutions within the Fortive Business System. If you have further questions or need assistance with applying these concepts, feel free to ask! Would you like to explore any specific examples or applications of these tools? | E17: Good | F17: P.Lee
A18: 17 | B18: Provide me with a Experiment card | C18: An Experiment Card is a valuable tool used in the Fortive Business System (FBS) to document and track experiments or tests conducted during a kaizen event or problem-solving process. It helps teams systematically test hypotheses, gather data, and analyze results to drive continuous improvement. Below is a template for an Experiment Card, along with explanations of each section. ### Experiment Card Template --- **Experiment Card** **Date:** _______________________ **Team Members:** _______________________________________________________ **Experiment Title:** ____________________________________________________ **Objective of the Experiment:** - Clearly state the purpose of the experiment and what you aim to achieve. - ______________________________________________________________________ - ______________________________________________________________________ **Hypothesis:** - Formulate a hypothesis that you intend to test through the experiment. - ______________________________________________________________________ - ______________________________________________________________________ **Background Information:** - Provide context or background information relevant to the experiment, including any previous findings or data that support the need for this experiment. - ______________________________________________________________________ - ______________________________________________________________________ **Methodology:** - Outline the steps you will take to conduct the experiment. Include details on how data will be collected and analyzed. - ______________________________________________________________________ - ______________________________________________________________________ **Data Collection Plan:** - Specify what data will be collected, how it will be measured, and the timeframe for data collection. - ______________________________________________________________________ - ______________________________________________________________________ **Expected Outcomes:** - Describe what you expect to find as a result of the experiment. - ______________________________________________________________________ - ______________________________________________________________________ **Results:** - After conducting the experiment, document the actual results and any observations made during the process. - ______________________________________________________________________ - ______________________________________________________________________ **Analysis:** - Analyze the results in relation to the hypothesis. Did the experiment support or refute your hypothesis? - ______________________________________________________________________ - ______________________________________________________________________ **Next Steps:** - Based on the results and analysis, outline the next steps or actions to be taken. - ______________________________________________________________________ - ______________________________________________________________________ **Notes:** - Include any additional notes or comments relevant to the experiment. - ______________________________________________________________________ - ______________________________________________________________________ --- ### Example of a Completed Experiment Card Section **Experiment Title:** Improve Production Efficiency **Objective of the Experiment:** - To determine if implementing a new workflow will reduce production time by 15%. **Hypothesis:** - Implementing a streamlined workflow will decrease production time and increase output. **Background Information:** - Previous data indicated that production time averaged 10 hours per unit. A review of the current workflow revealed several bottlenecks. **Methodology:** - Implement the new workflow for one week and compare production times to the previous week. **Data Collection Plan:** - Measure production time for each unit produced during the experiment and compare it to the baseline data collected from the previous week. **Expected Outcomes:** - A reduction in average production time to 8.5 hours per unit. **Results:** - Average production time during the experiment was 8.2 hours per unit. **Analysis:** - The results support the hypothesis, indicating that the new workflow is effective in reducing production time. **Next Steps:** - Standardize the new workflow across all production lines and monitor for further improvements. ### Conclusion This Experiment Card template can be customized to fit the specific needs of your experiments within the kaizen framework. By documenting your experiments systematically, you can enhance communication, track progress, and ensure that improvements are based on data-driven insights. If you need further assistance in filling out the Experiment Card or have specific questions about conducting experiments, feel free to ask! Would you like to explore any particular aspect further? | E18: Bad | F18: P.Lee Prompt is asking for an experiment card. It should be providing a link to the Templates tab for the actual experiment card. It is not asking WHAT is an experiment card.
A19: 18 | B19: provide me with the excel template to track all my experiments | C19: To effectively track experiments within the Fortive Business System (FBS), particularly during kaizen events, an Excel template can be a valuable tool. Below is a structured outline for an Excel template that you can use to document and monitor your experiments. This template includes key sections that will help you organize your data and analyze the results systematically. ### Excel Template Structure for Tracking Experiments You can create an Excel spreadsheet with the following columns: | **Experiment ID** | **Experiment Title** | **Date** | **Objective** | **Hypothesis** | **Methodology** | **Data Collection Plan** | **Expected Outcomes** | **Results** | **Analysis** | **Next Steps** | **Notes** | |--------------------|----------------------|----------|----------------|----------------|------------------|-------------------------|----------------------|-------------|--------------|---------------|-----------| | 1 | Improve Production Efficiency | 01/01/2023 | Reduce production time by 15% | New workflow will decrease production time | Implement new workflow for one week | Measure production time for each unit | Average production time to 8.5 hours | Average production time was 8.2 hours | Results support hypothesis | Standardize new workflow | Additional training needed | ### Detailed Explanation of Each Column 1. **Experiment ID**: A unique identifier for each experiment to facilitate tracking. 2. **Experiment Title**: A brief title that summarizes the focus of the experiment. 3. **Date**: The date when the experiment is initiated. 4. **Objective**: Clearly state the purpose of the experiment and what you aim to achieve. 5. **Hypothesis**: Formulate a hypothesis that you intend to test through the experiment. 6. **Methodology**: Outline the steps you will take to conduct the experiment. 7. **Data Collection Plan**: Specify what data will be collected, how it will be measured, and the timeframe for data collection. 8. **Expected Outcomes**: Describe what you expect to find as a result of the experiment. 9. **Results**: Document the actual results and any observations made during the process. 10. **Analysis**: Analyze the results in relation to the hypothesis. Did the experiment support or refute your hypothesis? 11. **Next Steps**: Based on the results and analysis, outline the next steps or actions to be taken. 12. **Notes**: Include any additional notes or comments relevant to the experiment. ### Example of How to Use the Template 1. **Experiment ID**: 1 2. **Experiment Title**: Improve Production Efficiency 3. **Date**: 01/01/2023 4. **Objective**: Reduce production time by 15% 5. **Hypothesis**: Implementing a streamlined workflow will decrease production time and increase output. 6. **Methodology**: Implement the new workflow for one week and compare production times to the previous week. 7. **Data Collection Plan**: Measure production time for each unit produced during the experiment and compare it to the baseline data collected from the previous week. 8. **Expected Outcomes**: A reduction in average production time to 8.5 hours per unit. 9. **Results**: Average production time during the experiment was 8.2 hours per unit. 10. **Analysis**: The results support the hypothesis, indicating that the new workflow is effective in reducing production time. 11. **Next Steps**: Standardize the new workflow across all production lines and monitor for further improvements. 12. **Notes**: Consider additional training for staff on the new workflow. ### Conclusion This Excel template provides a structured approach to tracking experiments, ensuring that all relevant information is documented and easily accessible. By using this template, you can enhance communication within your team and facilitate data-driven decision-making during kaizen events and other improvement initiatives. If you need further assistance in setting up the Excel file or have specific questions about tracking experiments, feel free to ask! Would you like to explore any particular aspect further? | E19: Bad | F19: P.Lee Experimentation database to track experiments conducted is located in the FBS Templates. It should not be recreating anything. It should be providing a link to the right location
A20: 19 | B20: How do I properly do a VOC? What are the key things I need to take into consideration? | C20: Conducting a Voice of the Customer (VOC) exercise is a critical component of the Fortive Business System (FBS) that helps organizations understand customer needs, preferences, and expectations. Properly executing a VOC initiative involves several key steps and considerations. Here’s a comprehensive guide on how to effectively conduct a VOC and what to keep in mind: ### Steps to Conduct a VOC 1. **Define Objectives** - **Action**: Clearly outline the goals of the VOC initiative. What specific information do you want to gather from customers? This could include feedback on product features, service quality, or overall satisfaction. - **Example**: If launching a new product, the objective might be to understand customer expectations regarding functionality and pricing. 2. **Identify Target Customers** - **Action**: Determine which customer segments you want to engage. This could include current customers, potential customers, or specific demographic groups. - **Example**: For a software product, you might target existing users, trial users, and industry experts to gather diverse insights. 3. **Select Data Collection Methods** - **Action**: Choose appropriate methods for collecting customer feedback. Common methods include surveys, interviews, focus groups, and observational studies. - **Example**: Use online surveys to gather quantitative data and conduct in-depth interviews for qualitative insights. 4. **Develop Questions** - **Action**: Create clear and concise questions that align with your objectives. Ensure that questions are open-ended to encourage detailed responses, as well as closed-ended for quantitative analysis. - **Example**: - Open-ended: "What features do you find most valuable in our product?" - Closed-ended: "On a scale of 1 to 10, how satisfied are you with our customer service?" 5. **Engage with Customers** - **Action**: Reach out to customers using the selected methods. Ensure that the process is user-friendly and that customers feel their feedback is valued. - **Example**: Send personalized invitations to participate in surveys or interviews, highlighting how their input will influence future improvements. 6. **Analyze the Data** - **Action**: Once data is collected, analyze it to identify trends, patterns, and key insights. Use statistical tools for quantitative data and thematic analysis for qualitative feedback. - **Example**: If survey results show that 70% of customers desire a specific feature, this indicates a strong demand that should be prioritized. 7. **Communicate Findings** - **Action**: Share the insights gathered from the VOC with relevant stakeholders, including product development, marketing, and customer service teams. This ensures that everyone is aligned on customer needs. - **Example**: Create a report summarizing key findings and recommendations based on customer feedback. 8. **Implement Changes** - **Action**: Use the insights from the VOC to inform decision-making and drive improvements in products, services, or processes. - **Example**: If customers express a need for improved user interface design, prioritize this in the next product development cycle. 9. **Follow-Up with Customers** - **Action**: After implementing changes based on VOC feedback, follow up with customers to inform them of the improvements made and gather additional feedback. - **Example**: Send a communication to customers highlighting how their feedback led to specific changes, reinforcing their importance in the process. ### Key Considerations for VOC - **Customer-Centric Approach**: Always keep the customer at the center of your VOC efforts. Understand their pain points and preferences to drive meaningful improvements. - **Diverse Perspectives**: Ensure that you gather feedback from a broad range of customers to avoid blind spots. Different segments may have varying needs and expectations. - **Continuous Improvement**: Treat VOC as an ongoing process rather than a one-time event. Regularly engage with customers to stay updated on their evolving needs. - **Data Integrity**: Ensure that the data collected is reliable and valid. Use appropriate sampling methods and avoid leading questions that could bias responses. - **Actionable Insights**: Focus on gathering insights that can lead to actionable changes. Avoid collecting data for the sake of data; ensure it serves a purpose. ### Conclusion By following these steps and considerations, you can effectively conduct a Voice of the Customer initiative that aligns with the principles of the Fortive Business System. This approach will help you gather valuable insights that can drive continuous improvement and enhance customer satisfaction. If you have further questions or need assistance with specific aspects of conducting a VOC, feel free to ask! Would you like to explore any particular area in more detail? | E20: Neutral | F20: P.LEE TAGS definiton is not correct.
A21: 20 | B21: What specific problem statement should I formulate based on my current situation? | C21: Formulating a specific problem statement is a critical step in the Problem Solving Process (PSP) within the Fortive Business System (FBS). A well-defined problem statement helps clarify the issue at hand and guides the subsequent analysis and action planning. Here’s how to create an effective problem statement based on your current situation: ### Steps to Formulate a Problem Statement 1. **Identify the Current Situation** - **Action**: Begin by clearly describing the current state of affairs. What is happening that indicates a problem? - **Example**: "Production line A has been experiencing frequent delays." 2. **Define the Desired Outcome** - **Action**: Specify what the ideal or desired state looks like. What do you want to achieve? - **Example**: "The target is to achieve 95% on-time delivery for all products." 3. **Determine the Gap** - **Action**: Identify the discrepancy between the current situation and the desired outcome. This gap is crucial for understanding the significance of the problem. - **Example**: "Currently, on-time delivery is at 80%, resulting in a 15% gap from the target." 4. **Use the TAGS Framework** - **Action**: Structure your problem statement using the TAGS framework (Target, Actual, Gap, Scope). This ensures that all critical elements are included. - **Example**: - **Target**: 95% on-time delivery - **Actual**: 80% on-time delivery - **Gap**: 15% - **Scope**: Production line A for the last quarter. 5. **Draft the Problem Statement** - **Action**: Combine the elements into a clear and concise statement that captures the essence of the problem. - **Example**: "Production line A is currently achieving 80% on-time delivery, which is 15% below the target of 95%, resulting in delays that impact customer satisfaction and revenue." ### Example Problem Statement **Problem Statement**: "Production line A is currently achieving 80% on-time delivery, which is 15% below the target of 95%. This gap has resulted in increased customer complaints and a potential loss of revenue over the last quarter." ### Key Considerations - **Clarity**: Ensure that the problem statement is clear and easily understood by all stakeholders. - **Specificity**: Avoid vague language; be specific about the issue, the metrics involved, and the impact. - **Relevance**: Make sure the problem statement is relevant to the current situation and aligns with organizational goals. ### Conclusion By following these steps and utilizing the TAGS framework, you can formulate a specific problem statement that effectively captures the current situation and guides your problem-solving efforts. This structured approach aligns with the principles of the Fortive Business System and sets the stage for successful resolution of the identified issue. If you need further assistance in refining your problem statement or have specific details about your situation that you would like to discuss, feel free to ask! Would you like to explore any particular aspect further? | E21: Neutral | F21: P.Lee It is correct, but analyzing the prompt it seems like it is asking for guidance, it is correct to provide the how to do it, maybe helpful to ask what is the situation? Provide and ask the question what is the target you are trying to achieve? where are you currently at? How long has this been occuring? etc TAGS: TREND, ACTUAL, GAP, STANDARD
A22: 21 | B22: How can I ensure that my problem statement is clear and concise? | C22: Ensuring that your problem statement is clear and concise is crucial for effective problem-solving within the Fortive Business System (FBS) and the Problem Solving Process (PSP). A well-defined problem statement helps guide the analysis and actions needed to address the issue. Here are key steps and considerations to help you formulate a clear and concise problem statement: ### 1. **Use the TAGS Framework** - **Action**: Structure your problem statement using the TAGS framework, which stands for Target, Actual, Gap, and Scope. This framework helps ensure that all critical elements are included. - **Example**: - **Target**: 95% on-time delivery - **Actual**: 80% on-time delivery - **Gap**: 15% - **Scope**: Production line A for the last quarter. - **Problem Statement**: "Production line A is currently achieving 80% on-time delivery, which is 15% below the target of 95%." ### 2. **Be Specific and Focused** - **Action**: Avoid vague language and ensure that your statement is specific about the issue at hand. Focus on one problem at a time to prevent confusion. - **Example**: Instead of saying "We have quality issues," specify "The defect rate for product X has increased to 10% over the last month." ### 3. **Define the Impact** - **Action**: Clearly articulate the impact of the problem on the organization, customers, or processes. This helps convey the urgency and importance of addressing the issue. - **Example**: "The 15% gap in on-time delivery is resulting in increased customer complaints and potential loss of revenue." ### 4. **Keep It Concise** - **Action**: Aim for brevity while ensuring that all necessary information is included. A concise statement is easier to understand and communicate. - **Example**: "Production line A is achieving 80% on-time delivery, 15% below the target, leading to customer dissatisfaction." ### 5. **Use Clear Language** - **Action**: Avoid jargon or technical terms that may not be understood by all stakeholders. Use straightforward language that is accessible to everyone involved. - **Example**: Instead of using technical terms like "OEE" (Overall Equipment Effectiveness), you might say "The efficiency of the production line is lower than expected." ### 6. **Validate with Stakeholders** - **Action**: Share your problem statement with team members or stakeholders to ensure clarity and gather feedback. This collaborative approach can help refine the statement. - **Example**: Present the problem statement in a team meeting and ask for input on whether it accurately reflects the issue. ### 7. **Iterate as Necessary** - **Action**: Be open to revising the problem statement based on feedback and new insights. The problem may evolve as you gather more information. - **Example**: If new data reveals additional factors contributing to the problem, update the statement to reflect this broader understanding. ### Conclusion By following these steps and utilizing the TAGS framework, you can create a clear and concise problem statement that effectively captures the essence of the issue. This structured approach aligns with the principles of the Fortive Business System and sets the stage for successful resolution of the identified problem. If you need further assistance in refining your problem statement or have specific details about your situation that you would like to discuss, feel free to ask! Would you like to explore any particular aspect further? | E22: Neutral | F22: P.Lee TAGS: TREND, ACTUAL, GAP, STANDARD
A23: 22 | B23: What metrics should I use to define the success criteria for this problem? | C23: Defining success criteria through appropriate metrics is essential for evaluating the effectiveness of solutions implemented during the Problem Solving Process (PSP) within the Fortive Business System (FBS). The metrics you choose should align with the specific problem you are addressing and the goals you aim to achieve. Here’s a comprehensive guide on selecting metrics for defining success criteria: ### 1. **Identify the Problem and Objectives** - **Action**: Clearly define the problem you are addressing and the objectives you want to achieve. This will guide the selection of relevant metrics. - **Example**: If the problem is related to production delays, your objective might be to improve on-time delivery rates. ### 2. **Select Relevant Metrics** - **Action**: Choose metrics that directly reflect the performance related to the problem and objectives. Here are some common metrics to consider based on different scenarios: #### For Production and Operational Efficiency - **On-Time Delivery Rate**: Measures the percentage of products delivered on time compared to the total number of deliveries. - **Formula**: (Number of On-Time Deliveries / Total Deliveries) x 100 - **Example**: Target an on-time delivery rate of 95%. - **Cycle Time**: The total time taken to complete a process from start to finish. Reducing cycle time can indicate improved efficiency. - **Example**: Aim to reduce cycle time from 10 hours to 8 hours per unit. - **Overall Equipment Effectiveness (OEE)**: A measure of how effectively a manufacturing operation is utilized compared to its full potential. - **Formula**: OEE = Availability x Performance x Quality - **Example**: Target an OEE of 85%. #### For Quality Improvement - **Defect Rate**: The percentage of products that do not meet quality standards. - **Formula**: (Number of Defective Products / Total Products Produced) x 100 - **Example**: Aim to reduce the defect rate from 5% to 2%. - **Customer Satisfaction Score (CSAT)**: A measure of customer satisfaction with the product or service. - **Example**: Target a CSAT score of 90% or higher. #### For Financial Impact - **Cost Savings**: Measure the reduction in costs resulting from improvements. - **Example**: Calculate the cost savings achieved through reduced waste or improved efficiency. - **Revenue Growth**: Assess the increase in revenue as a result of improved processes or customer satisfaction. - **Example**: Target a revenue increase of 10% over the next quarter. ### 3. **Establish Baselines** - **Action**: Determine baseline values for each metric before implementing changes. This will allow you to measure improvement effectively. - **Example**: If the current on-time delivery rate is 80%, this will serve as your baseline for comparison after implementing improvements. ### 4. **Set Targets** - **Action**: Define specific, measurable targets for each metric that reflect the desired outcomes. - **Example**: Set a target to achieve a 15% improvement in on-time delivery rates within three months. ### 5. **Monitor and Review** - **Action**: Continuously monitor the selected metrics after implementing changes. Regularly review performance against the established targets to assess success. - **Example**: Conduct monthly reviews of on-time delivery rates and cycle times to track progress. ### Conclusion By selecting relevant metrics that align with your problem and objectives, establishing baselines, and setting clear targets, you can effectively define success criteria for your problem-solving efforts. This structured approach will help ensure that you can measure the impact of your actions and make data-driven decisions within the Fortive Business System. If you need further assistance in selecting specific metrics for your situation or have questions about how to implement this process, feel free to ask! Would you like to explore any particular aspect further? | E23: Neutral | F23: Plee not completely accurate, it makes sense to provide some examples of the metrics depending on the problem. I think a better answer should indicate something about Leading and Lagging indicators. Need to track both and understand what the relationship is. Providing feedback to see and understand where the POR - Point of recognition should be close to the Point of occurnece will be helpful. How can you see the problem early so we are not reactiting and course correcting after the fact. What are the upstream process conditions that needs to hold true so we can predict the results in the downstream process.
A24: 23 | B24: Are there any common pitfalls to avoid when defining the problem? | C24: Defining the problem accurately is a critical step in the Problem Solving Process (PSP) within the Fortive Business System (FBS). A well-defined problem statement sets the stage for effective analysis and solution development. However, there are several common pitfalls to avoid when defining the problem. Here’s a comprehensive overview: ### Common Pitfalls to Avoid When Defining the Problem 1. **Vagueness and Ambiguity** - **Issue**: A problem statement that is too vague or ambiguous can lead to confusion and misalignment among team members. - **Example**: Saying "We have quality issues" does not specify what the issues are or their impact. - **Solution**: Use clear and specific language. For instance, "The defect rate for product X has increased to 10% over the last month" provides clarity. 2. **Lack of Data Support** - **Issue**: Defining a problem without supporting data can lead to assumptions rather than facts, making it difficult to understand the true nature of the issue. - **Example**: Claiming "Sales are down" without data fails to provide context or insight into the reasons behind the decline. - **Solution**: Gather relevant data to support your problem statement. For example, "Sales have decreased by 15% over the last quarter, primarily in the Southeast region." 3. **Ignoring the Scope** - **Issue**: Failing to define the scope of the problem can result in addressing symptoms rather than the root cause, leading to ineffective solutions. - **Example**: A statement like "Customer complaints are increasing" does not clarify which products or services are affected. - **Solution**: Clearly outline the scope. For instance, "Customer complaints regarding product Y have increased by 25% in the last three months." 4. **Overlooking Stakeholder Perspectives** - **Issue**: Not considering the perspectives of all relevant stakeholders can lead to an incomplete understanding of the problem. - **Example**: Defining a problem based solely on management's viewpoint without input from frontline employees may miss critical insights. - **Solution**: Engage with a broad range of stakeholders to gather diverse perspectives. This can be done through interviews, surveys, or focus groups. 5. **Focusing on Symptoms Instead of Root Causes** - **Issue**: Defining the problem based on symptoms rather than underlying causes can lead to temporary fixes rather than sustainable solutions. - **Example**: Addressing "High employee turnover" without investigating the reasons behind it (e.g., lack of training, poor management) will not resolve the issue. - **Solution**: Use tools like the "5 Whys" to drill down to the root causes of the problem. 6. **Setting Unrealistic Expectations** - **Issue**: Defining a problem with expectations that are too ambitious or unrealistic can lead to frustration and disengagement from the problem-solving process. - **Example**: Stating "We need to eliminate all defects immediately" may not be feasible. - **Solution**: Set realistic and achievable goals. For example, "We aim to reduce defects by 50% over the next six months." 7. **Neglecting to Update the Problem Statement** - **Issue**: As new information is gathered, failing to update the problem statement can lead to outdated or irrelevant analyses. - **Example**: Continuing to work with an initial problem statement that no longer reflects the current situation can misguide efforts. - **Solution**: Regularly review and revise the problem statement as new data and insights are obtained. ### Conclusion By being aware of these common pitfalls and actively working to avoid them, you can ensure that your problem statement is clear, concise, and effective. This will facilitate a more structured and successful problem-solving process within the Fortive Business System, ultimately leading to better outcomes and continuous improvement. If you have specific scenarios or examples you would like to discuss further, feel free to ask! Would you like to explore any particular aspect in more detail? | E24: Bad | F24: PLEE: There are good answers at the beginning but it is going to deep and talking about *Symptoms and Rootcauses** this has nothing to do with defining the problem since you are still at the DEFINE stage. There is
A25: 24 | B25: How do I prioritize multiple problems if they arise simultaneously? | C25: Prioritizing multiple problems that arise simultaneously is a critical skill in the Problem Solving Process (PSP) within the Fortive Business System (FBS). Effective prioritization ensures that resources are allocated efficiently and that the most impactful issues are addressed first. Here’s a comprehensive approach to prioritizing problems: ### 1. **Assess the Impact** - **Action**: Evaluate the potential impact of each problem on the organization. Consider factors such as customer satisfaction, financial implications, operational efficiency, and employee morale. - **Example**: If one problem involves a significant drop in customer satisfaction due to product defects, while another involves minor delays in internal processes, the former should be prioritized due to its direct impact on revenue and reputation. ### 2. **Determine Urgency** - **Action**: Identify the urgency of each problem. Some issues may require immediate attention due to deadlines, regulatory compliance, or critical operational needs. - **Example**: A safety issue that poses a risk to employees should be addressed immediately, while a process improvement suggestion that can wait may be lower on the priority list. ### 3. **Use the 80/20 Rule (Pareto Principle)** - **Action**: Apply the Pareto Principle to identify which problems are likely to yield the greatest benefits when resolved. Focus on the 20% of problems that will lead to 80% of the improvement. - **Example**: If three problems are identified, and resolving one of them will eliminate a significant bottleneck affecting multiple processes, prioritize that problem. ### 4. **Engage Stakeholders** - **Action**: Involve key stakeholders in the prioritization process. Their insights can provide valuable context and help identify which problems are most critical from different perspectives. - **Example**: Conduct a quick survey or meeting with team members to gather input on which issues they believe should be prioritized based on their experiences. ### 5. **Utilize a Prioritization Matrix** - **Action**: Create a prioritization matrix that evaluates problems based on criteria such as impact, urgency, and resources required. This visual tool can help clarify priorities. - **Example**: Use a simple 2x2 matrix with "High Impact" and "Low Impact" on one axis and "Urgent" and "Not Urgent" on the other. Place each problem in the appropriate quadrant to visualize priorities. ### 6. **Consider Resource Availability** - **Action**: Assess the resources available for addressing each problem, including time, personnel, and budget. Prioritize problems that can be resolved with the resources at hand. - **Example**: If one problem requires specialized expertise that is currently unavailable, it may need to be deprioritized in favor of issues that can be addressed immediately. ### 7. **Document and Communicate Priorities** - **Action**: Once priorities are established, document them clearly and communicate them to all relevant stakeholders. This ensures alignment and understanding of the focus areas. - **Example**: Create a simple report or presentation outlining the prioritized problems, the rationale for their prioritization, and the action plan for addressing them. ### 8. **Review and Adjust Regularly** - **Action**: Regularly review the prioritization as new information arises or as circumstances change. Be flexible and willing to adjust priorities based on evolving needs. - **Example**: If a new urgent issue arises that significantly impacts customer satisfaction, reassess the current priorities and adjust the action plan accordingly. ### Conclusion By following these steps, you can effectively prioritize multiple problems that arise simultaneously, ensuring that your team focuses on the most critical issues first. This structured approach aligns with the principles of the Fortive Business System and supports continuous improvement efforts. If you have specific problems you are facing or need further assistance with prioritization, feel free to ask! Would you like to explore any particular aspect further? | E25: Good | F25: P.Lee
... A45: 44 | B45: What resources are available for further training on the PSP methodology? | C45: To enhance your understanding and application of the Problem Solving Process (PSP) methodology within the Fortive Business System (FBS), several resources are available for further training. Here’s a structured overview of these resources: ### 1. **Digital Learning Courses** - **PSP Digital Learning Course**: This course is specifically designed to provide a comprehensive overview of the PSP methodology. It covers the framework, tools, and techniques necessary for effective problem-solving. Enrolling in this course will equip you with the knowledge to apply PSP in various business scenarios. - **Access**: You can find this course on the Fortive learning platform or through the FBS training portal. ### 2. **Kaizen Event Basics Course** - **Overview**: This course focuses on the principles of kaizen, which is integral to the PSP. It teaches participants how to plan, execute, and sustain continuous improvement efforts through kaizen events. - **Duration**: Approximately 1 hour. - **Content**: The course includes practical examples and case studies that illustrate the application of kaizen in conjunction with the PSP. - **Access**: Available on the Fortive learning platform. ### 3. **FBS Learning Documents** - **Comprehensive Resources**: The FBS knowledge base contains various documents and presentations that detail the PSP methodology and its application. These resources include: - **Case Studies**: Real-world examples of PSP applications within Fortive, such as the Super Bank case study, which highlights process improvement efforts. - **Glossary and Acronyms**: Understanding the terminology used in FBS can enhance your comprehension of the PSP framework. - **Access**: These documents can be accessed through the Fortive SharePoint site or the FBS knowledge base. ### 4. **Workshops and Training Sessions** - **In-Person or Virtual Workshops**: Fortive often conducts workshops that focus on the PSP and related methodologies. These sessions provide hands-on experience and the opportunity to collaborate with peers. - **Networking**: Engaging in these workshops allows you to network with other employees who are also applying PSP, facilitating knowledge sharing and best practices. ### 5. **Mentorship and Coaching** - **On-the-Job Training**: Seek mentorship from experienced colleagues who have successfully applied the PSP methodology. They can provide insights, guidance, and support as you work on your own problem-solving initiatives. - **Peer Learning**: Form study groups or peer learning sessions to discuss challenges and share experiences related to the PSP. ### 6. **Continuous Improvement Resources** - **FBS Fundamentals**: Familiarize yourself with other FBS tools and methodologies that complement the PSP, such as Value Stream Mapping (VSM), Daily Management (DM), and Standard Work. Understanding these tools will enhance your overall problem-solving capabilities. - **Access**: Resources related to these methodologies are also available on the Fortive learning platform and SharePoint. ### Conclusion By utilizing these resources, you can deepen your understanding of the Problem Solving Process and enhance your ability to apply it effectively within the Fortive Business System. Engaging in training courses, accessing learning documents, participating in workshops, and seeking mentorship will all contribute to your professional development in this area. I found related documents in our FBS knowledge base. Would you like me to search for more specific aspects of this topic? | E45: Neutral | F45: P:Lee One thing I will update is to indicate Instructor Led bootcamps - to check with the FBS schedule, the joining a PSP kaizen seeing it in action, and applying the PSP process in your dialy work. Practice, practice, practice. Then reach out to the the PSP champions for further guidance.

Sheet VSM Mentor Prompts
A1: SL | B1: Prompts | C1: Response | D1: Sources | E1: Status | F1: Tester Remarks | G1: Developer Remarks | H1: Date
A2: 1 | B2: VSM - When to use? | C2: Value Stream Mapping (VSM) is beneficial when applied to the right problem. However, it is not a universal tool and should be used selectively based on the specific challenges in your workflows or systems. | D2: https://fortive.sharepoint.com/:p:/r/sites/FTV-TheFort/_layouts/15/Doc.aspx?sourcedoc=%7B8E18CC86-963B-402D-9A5F-30E27D5ECE6C%7D&file=value-stream-mapping-tied%20to%20elearning.pptx&action=edit&mobileredirect=true | E2: Bad | F2: P.Lee Where did this answer come from? This is a fundamental tool. Where did the wordings not a Universal tool come from?
A3: 2 | B3: Steps in building a VSM | C3: The process of building a Value Stream Map includes creating a graphic representation of the flow of information and materials in a process or service. One key step is creating a Future State Value Stream Map to visualize how the process can be optimized. This helps identify problems and inconsistencies where customer expectations are not being met. While specific detailed steps are not listed, the focus is on understanding and improving the current state towards a future, streamlined flow. | D3: https://fortive.sharepoint.com/:p:/r/sites/FTV-TheFort/Shared%20Documents/_2025/Projects/KATA/Project%20Plan/Data/Kata%20files/FBS%20Learning%20Documents/value-stream-mapping-tied%20to%20elearning.pptx?d=w8e18cc86963b402d9a5f30e27d5ece6c&csf=1&web=1&e=mSg8f4 | E3: Bad | F3: P.Lee This is asking for steps in a VSM. I think the VSM mentor should be able to define and list out all the steps. Not a generic answer.
A4: 3 | B4: How to convert inventory in unit of work (quotes, propects, lines, devices etc.) to units of Time | C4: To convert inventory in units of work into units of time, you need to use the lead time calculation approach. Take the total inventory count of the work items (e.g., quotes, prospects, etc.) and divide this by the daily demand (how many items are processed or completed daily). This gives you the amount of wait time tied up in the inventory. Example Calculation: - Inventory: 100 prospects - Daily Demand: 20 prospects/day - Lead Time: 100 ÷ 20 = 5 days This method translates inventory quantity into the associated waiting time for completion. | D4: https://fortive.sharepoint.com/:p:/r/sites/FTV-TheFort/_layouts/15/Doc.aspx?sourcedoc=%7B8E18CC86-963B-402D-9A5F-30E27D5ECE6C%7D&file=value-stream-mapping-tied%20to%20elearning.pptx&action=edit&mobileredirect=true | E4: Good | F4: V. Akella
A5: 4 | B5: What is TAKT time | C5: TAKT time represents the regular pulse set by customer demand. It is calculated using the formula: TAKT TIME = Total Available Production Time ÷ Average Customer Demand This calculation helps determine the maximum time your processes can take to meet customer expectations. It’s usually performed in seconds or minutes and aligns your production to the pace required by customers. | D5: https://fortive.sharepoint.com/:p:/r/sites/FTV-TheFort/_layouts/15/Doc.aspx?sourcedoc=%7B8E18CC86-963B-402D-9A5F-30E27D5ECE6C%7D&file=value-stream-mapping-tied%20to%20elearning.pptx&action=edit&mobileredirect=true | E5: Good | F5: P.Lee should just be Total available Productive Time. Need to correct source
A6: 5 | B6: Process Time Vs Lead time | C6: Process Time is the cycle time required to complete work without interruptions, while Lead Time represents the total wait time (such as inventory waiting to be processed). Both are essential for completing the timeline of a Current State Value Stream Map. | D6: https://fortive.sharepoint.com/:p:/r/sites/FTV-TheFort/_layouts/15/Doc.aspx?sourcedoc=%7B8E18CC86-963B-402D-9A5F-30E27D5ECE6C%7D&file=value-stream-mapping-tied%20to%20elearning.pptx&action=edit&mobileredirect=true | E6: Good | F6: P.Lee Should update the training deck to change - provide more clarity in LT and Processing time & associating wait time. We need to update the VSM to align these concepts - correct and align in TPI, SW
A7: 6 | B7: What to fill in Process box? | C7: In the Process box, you should detail each activity required to fulfill a customer request within the value stream. These activities are part of the sequence that ensures the delivery of the product or service to the customer. Avoid adding swim lanes or decision diamonds, as VSM is not meant to be a detailed process map. | D7: https://fortive.sharepoint.com/:p:/r/sites/FTV-TheFort/_layouts/15/Doc.aspx?sourcedoc=%7B8E18CC86-963B-402D-9A5F-30E27D5ECE6C%7D&file=value-stream-mapping-tied%20to%20elearning.pptx&action=edit&mobileredirect=true | E7: Good | F7: P.Lee & V.Akella
A8: 7 | B8: Information flow - what does that mean? | C8: In the context of Value Stream Mapping, information flow refers to the movement and communication of data necessary to complete a product or service. It helps teams visualize and understand inefficiencies in their processes, specifically showing where material or service delivery may not align with customer expectations. | D8: https://fortive.sharepoint.com/:p:/r/sites/FTV-TheFort/_layouts/15/Doc.aspx?sourcedoc=%7B8E18CC86-963B-402D-9A5F-30E27D5ECE6C%7D&file=value-stream-mapping-tied%20to%20elearning.pptx&action=edit&mobileredirect=true | E8: Good | F8: P.Lee & V.Akella right answer and pulling from system This would be a good one where you show an image of the zigzag arrow
A9: 8 | B9: Affinity Diagram for waste | C9: ### Template for Recording Waste This template is suited for documenting and organizing observations of waste. It can be applied effectively to streamline waste identification during value stream mapping through techniques like affinity diagrams. #### Key Features: - Categorizes waste types for easier analysis. - Provides a structured format to document waste observations. - Helps in organizing and prioritizing waste occurrences during process improvement initiatives. #### Access Link: <a href="https://fortive.sharepoint.com/sites/FBS/Shared%20Documents/Waste%20Recording%20Form.xlsx?d=w45ff08d1b13049bc98c3232db6b075df&csf=1&web=1&e=OepEri" target="_blank" rel="noopener noreferrer">Download Waste Recording Form</a> This resource directly facilitates teams engaged in identifying and addressing inefficiencies within a value stream. | D9: https://fortive.sharepoint.com/sites/FBS/Shared%20Documents/Waste%20Recording%20Form.xlsx?d=w45ff08d1b13049bc98c3232db6b075df&csf=1&web=1&e=OepEri | E9: Neutral | F9: P.Lee & V.Akella Where did this question generated from? Where does the access link take you? There is no specific affinity diagram just for waste. We have an affinity diagram template that can be used when prioritizing which one to work on
A10: 9 | B10: Prioritiztion matrix for Kaizen | C10: ### Prioritization Tool for Kaizen Events To support prioritization during Kaizen events, an **Impact Matrix Template** is available. This resource helps teams structure and rank items based on their impact and feasibility. #### Key Features: - Categorizes initiatives for effective prioritization. - Identifies high-impact, high-feasibility actions to streamline decision-making. #### Template Access: You can download the template directly using the following link: <a href="https://fortive.sharepoint.com/sites/FBS/Shared%20Documents/Impact%20Matrix.pptx?d=wf6a814ba5ede40b69088cf84fb4e6baf&csf=1&web=1&e=Aq27os" target="_blank" rel="noopener noreferrer">Download Impact Matrix Template</a> #### Recommendation: Ensure the matrix is customized to reflect the specific goals and metrics of your Value Stream Mapping and Kaizen event objectives. | D10: https://fortive.sharepoint.com/:p:/r/sites/FBS/_layouts/15/Doc.aspx?sourcedoc=%7BF6A814BA-5EDE-40B6-9088-CF84FB4E6BAF%7D&file=Impact%20Matrix.pptx&action=edit&mobileredirect=true | E10: Good | F10: P.Lee & V.Akella
A11: 10 | B11: Kaizen charter template | C11: ### Kaizen Charter Template A ready-to-use Kaizen Charter template for planning and executing Kaizen events is available in the 'Kaizen event basics' category. You can access it through the following link: - **<a href="https://fortive.sharepoint.com/sites/FBS/Shared%20Documents/Fortive-Kaizen-Charter%202022.xlsx?d=w217854ef74444dfc9d56cb7fb197fe23&csf=1&web=1&e=A8VluV" target="_blank" rel="noopener noreferrer">Download the Kaizen Charter Template</a>** This template assists in defining objectives, scope, and responsibilities specific to Kaizen activities, such as Value Stream Mapping (VSM). | D11: https://fortive.sharepoint.com/sites/FBS/Shared%20Documents/Fortive-Kaizen-Charter%202022.xlsx?d=w217854ef74444dfc9d56cb7fb197fe23&csf=1&web=1&e=A8VluV | E11: Bad | F11: Link is not working
A12: 11 | B12: Action plan template | C12: **Source:** <a href="https://fortive.sharepoint.com/:x:/r/sites/FBS/Shared%20Documents/2018%20Action%20Plan%20Template%20Ver4_.xls?d=w8b3015f5d6a94e28a98f37f2cd29d88d&csf=1&web=1&e=ujyswj" target="_blank" rel="noopener noreferrer">2018 Action Plan Template Ver4</a> **Description:** The template provided offers a structured format for creating an action plan tailored for Value Stream Mapping. Include key sections such as task details, responsible person, timeline, and metrics. You can download the file directly from the linked resource. | D12: https://fortive.sharepoint.com/:x:/r/sites/FBS/Shared%20Documents/2018%20Action%20Plan%20Template%20Ver4_.xls?d=w8b3015f5d6a94e28a98f37f2cd29d88d&csf=1&web=1&e=ujyswj | E12: Bad | F12: Link goes to an action plan with dates 2023 and 2024.
A13: 12 | B13: Miro board template for VSM | C13: ### Information Unavailable Currently, there isn't a specific reference to a Miro board template designed for Value Stream Mapping in the search results provided. You may consider exploring Miro's official template library or reaching out directly to Miro's support for assistance. ### Suggested Next Steps - Check Miro's <a href="https://miro.com/templates/" target="_blank" rel="noopener noreferrer">template library</a> for Value Stream Mapping options. - Contact Miro’s customer support for guidance on accessing specific templates for your use case. | D13: https://miro.com/templates/ | E13: Good | F13: VSM template with FBS Bite Links - Miro We need to create a central repository of where to find the boards.
A14: 13 | B14: What is the purpose of a Value Stream Mapping (VSM) process? | C14: The purpose of a Value Stream Mapping (VSM) process is to visually represent the flow of materials and information in a process or service. It helps identify waste, evaluate how each process step adds value from the customer's perspective, and uncover problems or inconsistencies that hinder meeting customer expectations. | E14: Good | F14: P.Lee & V.Akella
A15: 14 | B15: How do you calculate lead time and cycle time in VSM? | C15: In Value Stream Mapping (VSM), Lead Time and Cycle Time are vital metrics for understanding flow and identifying bottlenecks. **Lead Time:** This measures the waiting time. It encompasses how long inventory or work items remain in queue before processing begins. To calculate, sum up all the wait times between process steps. **Cycle Time (Process Time):** This is the uninterrupted time required to complete the actual work. It doesn't include waiting or idle times. Sum up the duration of actual processing for each step. By adding these metrics to your timeline, you can construct a complete Current State Value Stream Map and locate inefficiencies efficiently. | E15: Good | F15: P.Lee & V.Akella Our material is off, we need to update the source
A16: 15 | B16: How does bottleneck identification improve flow efficiency? | C16: Identifying bottlenecks is crucial for improving flow efficiency because bottlenecks cause process delays and capacity constraints, as highlighted in Value Stream Mapping (VSM). By targeting these bottlenecks, you can optimize the flow of materials and information across the entire system, reducing cycle time and work-in-progress (WIP). This leads to a smoother, more efficient value stream with reduced waste and enhanced delivery outcomes. | E16: Good | F16: P.Lee & V.Akella
A17: 16 | B17: Can you describe an example of a simple VSM visual? | C17: ### Example of a Simple Value Stream Mapping (VSM) Visual **Value Stream Map (VSM)** is a tool used to visualize and analyze the flow of materials and information required to bring a product or service to a customer. Here's an outline of the basic components of a typical Value Stream Map: 1. **Process Steps:** Represented as rectangles or process blocks showing major steps in the workflow (e.g., 'Order Processing,' 'Manufacturing,' 'Shipping'). 2. **Material Flow:** Arrows depict the movement of materials or products between process steps. 3. **Information Flow:** Lines or arrows (usually dashed) showing the flow of information (e.g., orders, scheduling, etc.) between the customer, processes, and suppliers. 4. **Inventory Icons:** Triangles can be used to visually represent inventory between production steps. 5. **Key Metrics:** Metrics such as cycle time (CT), lead time (LT), and takt time (TT) are listed below each process block. --- ### Simple VSM Example (Text-based layout): **Customer** → Order Received → | Cycle Time: 2 mins | → Manufacturing → | Cycle Time: 5 mins | → Packaging → | Cycle Time: 3 mins | → **Shipping** → Delivery Completed. Material Flow: `---Straight Arrow--->` Information Flow: `--- Dashed Lines --->` --- This is a simple linear example, but tools and templates typically provide diagrammatic representations. If you're looking for a related template, further context would be needed. | E17: Neutral | F17: Need to display a picture of VSM. The description does not mention Data sources for varoius steps which is also documented in a VSM.
A18: 17 | B18: What is the role of WIP (Work in Progress) in analyzing a value stream? | C18: Work in Process (WIP) represents areas where there is inventory or tasks waiting in a queue for further processing. In Value Stream Mapping (VSM), WIP is used to identify bottlenecks or inefficiencies in the flow of work. By pinpointing locations where WIP builds up, teams can target delays and optimize flow for improved cycle time and lead time. The circle-with-lines icon visually indicates WIP levels in a value stream map. | D18: https://fortive.sharepoint.com/:p:/r/sites/FTV-TheFort/_layouts/15/Doc.aspx?sourcedoc=%7BAFDE1D59-E59F-49B8-AB60-2C268103BE0B%7D&file=standard-work-tied%20to%20elearning.pptx&action=edit&mobileredirect=true | E18: Neutral | F18: P.Lee & V.Akella Correct answer, but why is this pulling from SW link for the definition. Is there not any from the VSM module?
A19: 18 | B19: What steps are involved in the VSM Process? | C19: The provided documents do not detail the steps involved in the Value Stream Mapping process. However, Value Stream Mapping generally involves visually representing the flow of materials and information to identify inefficiencies and areas not meeting customer expectations. Let me know if you'd like assistance understanding specific VSM-related concepts! | E19: Bad | F19: P.Lee & V.Akella
A20: 19 | B20: Explain the importance of reading "Learning to See" before conducting VSM. | C20: The book 'Learning to See' is foundational for understanding Value Stream Mapping as it introduces key concepts and techniques. By reading it beforehand, individuals can grasp how to visually represent material and information flows essential to completing a product or service. This prepares teams to effectively identify bottlenecks, analyze flow efficiency, and optimize cycle and lead times during the mapping exercise. | D20: https://fortive.sharepoint.com/:p:/r/sites/FTV-TheFort/_layouts/15/Doc.aspx?sourcedoc=%7B8E18CC86-963B-402D-9A5F-30E27D5ECE6C%7D&file=value-stream-mapping-tied%20to%20elearning.pptx&action=edit&mobileredirect=true | E20: Bad | F20: The source link opens a the PDF document that is blury in some sections. Where is the source for the "Learning to see"?
A21: 20 | B21: What is the use of a Gemba kit during a VSM event? | C21: A Gemba kit is used during a VSM event to facilitate the team's understanding of the actual processes and to collect accurate data. It includes materials like the Gemba Packet and PPT Deck, which help guide the team in observing and analyzing the value stream directly at the 'Gemba' (real place where work happens). This ensures informed decision-making and helps identify bottlenecks or inefficiencies clearly. | E21: Neutral | F21: Not a good question
A22: 21 | B22: How does one prepare for a VSM session according to the provided documents? | C22: The preparation for a Value Stream Mapping session involves understanding the flow of materials and information required for a product or service. This process visually illustrates how activities align, forming a baseline for improvement. While the provided documents don't detail preparation steps, it's implied that grasping VSM principles and the concept of mapping flows is essential. | E22: Good | F22: What is the "Porovided document" referenced in the response?
A23: 22 | B23: Why is bringing a VSM from an OpCo important for external teams? | C23: Bringing a Value Stream Map (VSM) from an OpCo is important for external teams because it fosters a customer-centric approach to improving outcomes like Quality, Delivery, and Cost. VSM encourages system thinking by allowing external teams to see the entire value creation flow, rather than focusing on isolated optimization efforts. This helps identify interactions between processes, uncover unnoticed inefficiencies, and highlight best practices that can be replicated. Additionally, it enables effective problem-solving by collaboratively addressing root causes and targeting areas of improvement with minimal effort. | E23: Good | F23: P.Lee & V. Akella
A24: 23 | B24: Where are the current bottlenecks in the value stream, and how are they impacting lead time and flow efficiency? | C24: Value Stream Mapping (VSM), as a visual tool, is instrumental for pinpointing bottlenecks that disrupt process flow efficiency and extend lead times. By assessing each significant step in the stream, VSM evaluates how each adds value from a customer’s perspective while identifying waste at any level of the organization. To locate the current bottlenecks, map the end-to-end process comprehensively, highlighting areas with excessive Work-in-Progress (WIP), extended cycle times, or interruptions in flow. Bottlenecks typically diminish flow efficiency by causing delays, increase lead times, and obstruct timely delivery. Address them for improved throughput and customer satisfaction. | E24: Good | F24: P.Lee & V. Akella
A25: 24 | B25: What insights does the Current State VSM reveal about Work in Progress (WIP) levels, and do any steps show excessive waiting or inefficiencies? | C25: A Current State Value Stream Map typically highlights areas where Work in Progress (WIP) levels are high, contributing to inefficiencies like excessive waiting times. By visualizing the flow, you can spot bottlenecks caused by delays, over-processing, or inventory buildup, which might result from capacity constraints or unnecessary motion. For example, wastes such as 'waiting' and 'over-production' often manifest through prolonged lead times or rework cycles. Observing the stream firsthand will ensure no high-impact wastes are missed, including unused human potential or excessive downtime at specific stages. Focus on steps with significant delays or hold-ups to identify opportunities to streamline flow and reduce WIP. Tip: Be sure to experience the flow yourself to fully understand these inefficiencies. | E25: Good | F25: P.Lee & V. Akella
A26: 25 | B26: How is takt time calculated, and how aligned are the current processes to this takt time? | C26: Takt time is calculated as the pace of producing a product or service needed to meet customer demand. It is determined using a formula and is typically measured in seconds or minutes. To evaluate whether your current processes align with this takt time, you may wish to compare the observed **Process Time (Cycle Time)**—the time it takes to start and finish one unit of product or service—with your calculated takt time. If process times exceed takt time, the system may not be meeting customer demand efficiently, highlighting potential bottlenecks or areas of non-value-added activities. Analyzing this alignment will help identify whether resources are appropriately balanced or if adjustments are needed to improve flow efficiency. | E26: Good | F26: P.Lee & V. Akella
A27: 26 | B27: Which steps in the value stream are adding the least value, and how could these processes be improved or eliminated? | C27: To determine which steps add the least value, evaluate each process step from the customer's perspective. Use the Value Stream Map and go to Gemba to gather real data about each step. Look for inefficiencies classified as Muda (waste) such as overproduction, waiting, unnecessary movements, or defects. Document these observations and place opportunities for improvement into a Kaizen funnel. Eliminating waste is key, so focus on automating, streamlining, or removing redundant processes identified during the mapping. | E27: Good
A28: 27 | B28: What Kaizen bursts or improvement areas have been identified, and what would their immediate and long-term impact be? | C28: Kaizen bursts in the context of VSM are specific improvement opportunities identified during the mapping process. They prioritize areas of waste or bottlenecks for immediate and long-term optimization. Immediate impacts of these bursts often include streamlined workflows, reduced cycle times, and improved flow efficiency. Long-term impacts can extend to better alignment with strategic goals, reduced lead times, and enhanced collaboration of stream-aligned teams. The identification and prioritization of these bursts are integral to driving continuous improvement in the value stream as part of the PDCA (Plan-Do-Check-Act) cycle. | E28: Good
A29: 28 | B29: What elements from the current state map need to change to achieve a future state with better cycle times and reduced waste? | C29: To achieve a future state with better cycle times and reduced waste, focus on the following elements from the current state map: 1. **Identify and Eliminate Bottlenecks**: Locate areas where flow stops or slows and implement process improvements to alleviate these constraints. 2. **Minimize Rework Loops**: Address error-prone steps and improve first pass yield to reduce the need for corrections. 3. **Reduce Inventory and Batching**: Focus on where materials or work-in-progress (WIP) are accumulating. Shift from batching to single-piece flow where feasible. 4. **Streamlining Duplication**: Remove redundant or duplicated steps to create a seamless process flow. 5. **Optimize Disconnects**: Address gaps in material and information flow to ensure continuous processing. 6. **Target Waste Areas**: Identify and remove activities that do not add value, such as unnecessary motion, waiting, and overproduction. By focusing on these elements, the future state map can be redrawn to showcase a leaner process with improved cycle times and reduced waste. | E29: Good | F29: P.Lee
A30: 29 | B30: How does marketing/sales alignment fit into the overall stream, and is there opportunity for system-level improvement there? | C30: { "title":"Marketing/Sales in the Value Stream", "content":"Marketing and sales alignment fits into the overall value stream by serving as the initial phases in the flow of information and material. Their role is critical as they set the tone for customer expectations and feed demand into the value creation process. Opportunities for system-level improvement could involve identifying waste or misalignment between marketing, sales, and subsequent process steps. Using Value Stream Mapping (VSM) principles, teams can evaluate how marketing/sales activities add value from the customer's perspective and identify areas where information flow could be streamlined. For example, VSM might reveal delays or inefficiencies in handing off leads to delivery teams or inconsistencies in communicated customer requirements. By promoting system thinking, VSM encourages teams to identify these dependencies and improve interactions across processes, thus enhancing the overall flow efficiency and customer-centric results." } | E30: Neutral | F30: P.Lee How was this question obtained and was this one of the questions asked by an individual as a prompt?
A31: 30 | B31: What "islands of success" exist, and how can their strategies be scaled to eliminate the surrounding waste? | C31: In the context of Value Stream Mapping (VSM), 'islands of success' refer to best practices or efficient, high-performing processes within a broader system that may otherwise contain inefficiencies ('a sea of waste'). By utilizing system thinking—a fundamental principle of VSM—you can analyze the entire value creation flow to identify these successful elements and evaluate how they can be scaled or duplicated elsewhere in the system. This approach ensures that improvements are not isolated but contribute meaningfully to reducing overall waste and enhancing flow efficiency. | E31: Good | F31: P.Lee & V. Akella
A32: 31 | B32: How will the proposed Future State Value Stream align with enterprise-wide goals or streamline team efforts? | C32: The Future State Value Stream Map is designed to reflect improved processes and streamlined workflows that align with enterprise-wide goals. This step usually includes mapping out desired efficiencies in cycle time, reducing WIP, and improving flow efficiency while ensuring alignment with team charters. By implementing the mapped Future State, teams can move towards cohesive actions and more effective collaboration, as outlined in the overall value stream mapping agenda. | D32: https://fortive.sharepoint.com/sites/FBS/SitePages/VSM_Facilitator_Leader%20Guide.pptx | E32: Good | F32: P.Lee & V. Akella

Sheet TPI Mentor Prompts
A1: SL | B1: Prompts | C1: Response | D1: Sources | E1: Status | F1: Tester Remarks | G1: Developer Remarks | H1: Date
A2: 1 | B2: Is the Mentorship system providing all the necessary process flow templates? | C2: The Mentorship system includes various TPI process flow templates such as the TPI Process Flow Gemba Questionnaire and Waste Recording Form. These templates assist in analyzing and documenting processes effectively. Additional guidance can be accessed in the Facilitator Guide and Kaizen Planning & Execution documents. | D2: https://fortive.sharepoint.com/sites/FBS/Shared%20Documents/TPI%20Process%20Flow%20Gemba%20Questionnaire.xlsx?d=wacb1737f62984c428bf5aa80debe4d7c&csf=1&web=1&e=5ffZ2y | E2: Neutral | F2: P.Lee & Vakella source page not working should include links to the templates identified.
A3: 2 | B3: Can the user download the 'TPI Process Flow Gemba Questionnaire' template seamlessly? | C3: ### Availability The 'TPI Process Flow Gemba Questionnaire' template is accessible via the provided SharePoint link: [Download Here](https://fortive.sharepoint.com/sites/FBS/Shared%20Documents/TPI%20Process%20Flow%20Gemba%20Questionnaire.xlsx?d=wacb1737f62984c428bf5aa80debe4d7c&csf=1&web=1&e=5ffZ2y). ### Instructions 1. **Click the above link**: It directs you to the specified page where you can view and download the template. 2. **Verify Access**: Ensure you have the necessary permissions to access the SharePoint directory associated with this document. 3. **Technical Notes**: If you experience access or download issues, check your login credentials for the SharePoint platform. | D3: https://fortive.sharepoint.com/sites/FBS/Shared%20Documents/TPI%20Process%20Flow%20Gemba%20Questionnaire.xlsx?d=wacb1737f62984c428bf5aa80debe4d7c&csf=1&web=1&e=5ffZ2y | E3: Good | F3: P.Lee & Vakella Need to make sure the files will are read only
A4: 3 | B4: Is the questionnaire's link accessible and functional? | C4: The document does not provide a direct functional hyperlink to the Gemba Questionnaire. Instead, it outlines questions to assess process steps during a Gemba walk. | E4: Bad | F4: BAD QUESTION, nothing to test here, don’t use for testing
A5: 4 | B5: Can users upload their completed questionnaires? | C5: The TPI process supports the use of specific forms like the Waste Recording Form and Gemba Questionnaire. However, there is no information in the provided documents indicating that users can upload completed questionnaires to an online platform. It is recommended to keep these documents for reference and process analysis during the Kaizen event. | E5: Bad | F5: What is the intent of this question? Why will someone upload the questionaire?
A6: 5 | B6: Are users able to input data directly into the mentor platform during the Gemba walkthrough? | C6: The Gemba walkthrough involves observing the process at 'the real place' where activities occur. Users typically collect data manually or using designated tools during the walkthrough. Inputting data directly into the mentor platform would depend on the tools and systems provided for that specific Gemba walk, such as a Gemba packet or digital tools prepared beforehand. | E6: Bad | F6: We don’t have this capability. User should download the file and save it somewhere.
A7: 6 | B7: Does the mentor display accurate questions based on the TPI Process Flow? | C7: Yes, the mentor's questions align with the TPI Process Flow stages and are designed to gather detailed information specific to each stage. These questions systematically address areas like defining the process, identifying wastes, verifying countermeasures, and ensuring sustainment, ensuring alignment with the TPI Kaizen process framework. | D7: https://fortive.sharepoint.com/:x:/r/sites/FBS/_layouts/15/Doc.aspx?sourcedoc=%7BACB1737F-6298-4C42-8BF5-AA80DEBE4D7C%7D&file=TPI%20Process%20Flow%20Gemba%20Questionnaire.xlsx&action=default&mobileredirect=true | E7: Bad | F7: We should not be asking these questions because we havent have any design discussion on this.
A8: 7 | B8: Are the questions structured to align with the transactional improvement goals? | C8: Yes, the questions in TPI are structured to align with the goals of transactional improvement. They focus on identifying inefficiencies using the 8 wastes framework, diagnosing bottlenecks, capturing baseline metrics, and validating countermeasures for sustainable improvement. | E8: Good
A9: 8 | B9: Is the system validating input entries correctly? | C9: This question seems to align with identifying **Quality Defects** (one of the 8 wastes) by probing for errors or rework in the process. Based on your inquiry, it appears you may be in **Stage 2 – Investigate the Wastes**. ### Detected Stage: Stage 2 – Investigate the Wastes ### What I Know About Your Progress: - You're identifying if system-validation inefficiencies could be causing Quality Defects in input entries. ### Next Steps: To move forward, let's dig deeper into diagnosing this waste more comprehensively: 1. What specific types of input errors (e.g., missing, incorrect, or duplicate information) are being encountered? 2. How frequently do these errors occur, and what are the consequences (e.g., rework, project delays)? 3. Are there any specific parts of the system where the validation process is weaker or more problematic? Once you document Quality Defects fully, we can proceed to map out other waste types or transition to testing countermeasures. Let me know your findings! | D9: https://fortive.sharepoint.com/:p:/r/sites/FTV-TheFort/_layouts/15/Doc.aspx?sourcedoc=%7BA210F317-23A9-4204-ACF5-21D339C9CEA6%7D&file=transactional-process-improvement-tied%20to%20elearning.pptx&action=edit&mobileredirect=true | E9: Good
A10: 9 | B10: Are conditional questions displayed as per the process stage? | C10: Yes, questions and guidance are tailored to the user's current process stage to ensure relevance. For example, during Stage 1, questions focus on defining the problem and gathering baseline metrics, while in Stage 2, questions target identifying specific types of waste in the process. The conditional flow ensures smooth stage progression. | E10: Good
A11: 10 | B11: Can the mentor integrate questions from the '5S Daily Checklist' template for overlap processes? | C11: The '5S Daily Checklist' template located [here](https://fortive.sharepoint.com/sites/FBS/Shared%20Documents/5S/4%20Doc%20needed%20for%205S/2%20-%205S%20Checklist%203%20Shift.xlsx?d=wadb491d9ce164cccbfa9071dcfcc4194&csf=1&web=1&e=TWIjWK) can be reviewed and customized to include questions that cover overlapping processes. ### Steps for Integration: 1. **Identify Overlapping Processes**: Understand the specific processes that share responsibilities or tasks. 2. **Review Checklist Sections**: Ensure each of the 5S areas (Sort, Set in Order, Shine, Standardize, Sustain) has relevant questions aligned with these overlapping processes. 3. **Insert Custom Questions**: Edit the template or add a new section specifically for overlap-related queries, ensuring it's clear and actionable. 4. **Review Before Use**: Validate with all involved teams to ensure clarity and effectiveness. For any additional changes or broader integration in overlapping processes, consider feedback loops to refine the checklist over time. | D11: https://fortive.sharepoint.com/sites/FBS/Shared%20Documents/5S/4%20Doc%20needed%20for%205S/2%20-%205S%20Checklist%203%20Shift.xlsx?d=wadb491d9ce164cccbfa9071dcfcc4194&csf=1&web=1&e=TWIjWK | E11: Good
A12: 11 | B12: Do suggested next steps from the mentor align with input responses? | C12: Mentor's suggested next steps should align with user input responses by addressing the user's current stage in the TPI Kaizen process, targeting specific challenges or gaps identified, and guiding actions relevant to progressing to the next stage. | E12: Good
A13: 12 | B13: Is the mentor generating accurate feedback based on completed questionnaires? | C13: To determine your stage in the TPI Kaizen process, I need more context about your current activities and challenges. Based on your input about feedback, let me ask: - Could you clarify if you're currently analyzing the feedback process (Stage 1 or 2), testing solutions to improve feedback accuracy (Stage 3), or ensuring the process remains effective (Stage 4)? - What are the specific issues or inefficiencies you've identified regarding feedback generation? Once I have more details, I can provide tailored guidance for your current stage. | E13: Good
A14: 13 | B14: Does the system export results and suggestions in a usable format? | C14: You appear to be asking a direct question about the TPI system's ability to export results and suggestions. This is not explicitly detailed in the provided documents, so I need further clarification of your context. If this relates to recording improvement outcomes or reporting progress, tools like Value Stream Mapping and Waste Recording Forms are commonly used to record and communicate findings within TPI processes. Could you confirm if you're asking about integrating TPI results into reporting, or if you're at a specific stage in the TPI process and need guidance? | E14: Good
A15: 14 | B15: Are historical data and recommendations retrievable? | C15: TPI emphasizes maintaining documentation for all stages of the process, such as baseline metrics, identified wastes, and tested countermeasures. This ensures that historical data and recommendations are retrievable for future analysis or audits. Such documentation typically includes Value Stream Maps, Waste Recording Forms, and KPI tracking dashboards, which serve as historical records. | D15: https://fortive.sharepoint.com/:p:/r/sites/FTV-TheFort/_layouts/15/Doc.aspx?sourcedoc=%7BA210F317-23A9-4204-ACF5-21D339C9CEA6%7D&file=transactional-process-improvement-tied%20to%20elearning.pptx&action=edit&mobileredirect=true | E15: Good
A16: 15 | B16: Are the templates and questions available across devices and platforms? | C16: Templates and questions for Transactional Process Improvement (TPI), such as the TPI Process Flow Gemba Questionnaire, are designed to be widely accessible. Special IT considerations ensure these resources can be accessed in various ways and on different platforms for convenience and efficiency. | E16: Good
A17: 16 | B17: Is the navigation intuitive for users conducting a TPI process walkthrough? | C17: The TPI process emphasizes using structured tools and templates, such as the Value Stream Map and the Waste Recording Form, to guide users through each stage. These resources are designed to ensure clarity and ease of use for identifying inefficiencies, testing countermeasures, and sustaining improvements. | E17: Good
A18: 17 | B18: Does the mentor offer troubleshooting tips when errors are encountered? | C18: Based on the provided TPI Kaizen framework: The role of the mentor is to guide users through improving transactional processes systematically. While not explicitly labeled as "troubleshooting," the mentor does provide targeted guidance and probing questions at each stage to address inefficiencies or barriers (e.g., investigating wastes, verifying countermeasures). For example, during Stage 3 - Verify Countermeasures: - The mentor would explore questions if solutions face issues, such as: "What risks or side effects were identified during testing?" or "Have you re-validated the countermeasure's effectiveness against the baseline metrics?" If you'd like, could you clarify an error scenario so we can delve deeper into possible troubleshooting steps? | E18: Bad
A19: 18 | B19: Does the mentor handle concurrent users efficiently? | C19: The mentor is designed to interact with users on a one-to-one basis, maintaining a focused and personalized dialogue. Concurrent users are handled independently, with the context of each conversation preserved without interference. | E19: Good
A20: 19 | B20: Are there any delays in template loading during heavy usage? | C20: It seems like you're assessing a possible "Waiting" waste in Stage 2 of the TPI Kaizen process. Could you clarify which process you're analyzing and provide context such as how these templates are used, who uses them, and any metrics you've observed about delay times during heavy usage? | E20: Good
A21: 20 | B21: Are modifications or updates to the questionnaire reflected immediately? | C21: The information provided does not specify whether modifications or updates to the TPI Process Flow Gemba Questionnaire are reflected immediately. It would likely depend on the platform or system used for managing the questionnaire. Shared digital versions typically allow for real-time updates, but this should be verified with the specific tool or system being used. | E21: Good
A22: 21 | B22: Is the system adhering to organizational data privacy policies? | C22: It seems like your inquiry is regarding adherence to data privacy policies, which may be relevant to analyzing constraints or quality defects in Stage 1 or 2 of the TPI Kaizen process. Please clarify if this question is related to assessing the current state of a process within the framework of TPI or if you're seeking factual guidance on privacy assessments. If you're inquiring about process adherence to organizational data privacy policies specifically, consider these questions: - Is ensuring data privacy compliance part of the constraints or key performance indicators (KPIs) in your process? - Are there documented instances where data privacy requirements are not met, contributing to defects or inefficiencies? Could you share more details for me to pinpoint the relevance to your process improvement efforts? | E22: Good

Sheet G&I Mentor Prompts
A1: SL | B1: Prompts | C1: Response | D1: Sources | E1: Remarks
